
{"totalTime": 1.6504604816436768, "genResults": {"instance": "gen-inst-1.param", "status": "sat", "seed": 1047895682, "SRTime": 0, "solverTime": 0.11079859733581543}, "instanceResults": {"instance": "./detailed-output/inst-1-1047895682.dzn", "status": "ok", "score": -1, "results": {"main": {"runs": [{"seed": None, "status": "C", "time": 0.3760967254638672, "extra": {"objs": [], "flattenStatus": "ok", "flattenTime": 0.168807, "instanceType": "unsat", "answerStatus": "unknown"}}]}, "oracle": {"runs": []}}}, "status": "ok", "score": -1}
{"totalTime": 1.6642179489135742, "genResults": {"instance": "gen-inst-1.param", "status": "sat", "seed": 1430553564, "SRTime": 0, "solverTime": 0.11227154731750488}, "instanceResults": {"instance": "./detailed-output/inst-1-1430553564.dzn", "status": "ok", "score": -1, "results": {"main": {"runs": [{"seed": None, "status": "C", "time": 0.37004804611206055, "extra": {"objs": [], "flattenStatus": "ok", "flattenTime": 0.169805, "instanceType": "unsat", "answerStatus": "unknown"}}]}, "oracle": {"runs": []}}}, "status": "ok", "score": -1}
{"totalTime": 1.6783854961395264, "genResults": {"instance": "gen-inst-1.param", "status": "sat", "seed": 1828174830, "SRTime": 0, "solverTime": 0.11257147789001465}, "instanceResults": {"instance": "./detailed-output/inst-1-1828174830.dzn", "status": "ok", "score": -1, "results": {"main": {"runs": [{"seed": None, "status": "C", "time": 0.3792426586151123, "extra": {"objs": [], "flattenStatus": "ok", "flattenTime": 0.171113, "instanceType": "unsat", "answerStatus": "unknown"}}]}, "oracle": {"runs": []}}}, "status": "ok", "score": -1}
{"totalTime": 1.6483893394470215, "genResults": {"instance": "gen-inst-1.param", "status": "sat", "seed": 542193560, "SRTime": 0, "solverTime": 0.11833810806274414}, "instanceResults": {"instance": "./detailed-output/inst-1-542193560.dzn", "status": "ok", "score": -1, "results": {"main": {"runs": [{"seed": None, "status": "C", "time": 0.3757350444793701, "extra": {"objs": [], "flattenStatus": "ok", "flattenTime": 0.172079, "instanceType": "unsat", "answerStatus": "unknown"}}]}, "oracle": {"runs": []}}}, "status": "ok", "score": -1}
{"totalTime": 1.675093650817871, "genResults": {"instance": "gen-inst-1.param", "status": "sat", "seed": 719061008, "SRTime": 0, "solverTime": 0.12043428421020508}, "instanceResults": {"instance": "./detailed-output/inst-1-719061008.dzn", "status": "ok", "score": -1, "results": {"main": {"runs": [{"seed": None, "status": "C", "time": 0.3652808666229248, "extra": {"objs": [], "flattenStatus": "ok", "flattenTime": 0.185932, "instanceType": "unsat", "answerStatus": "unknown"}}]}, "oracle": {"runs": []}}}, "status": "ok", "score": -1}
{"totalTime": 1.6916418075561523, "genResults": {"instance": "gen-inst-1.param", "status": "sat", "seed": 895807196, "SRTime": 0, "solverTime": 0.12922143936157227}, "instanceResults": {"instance": "./detailed-output/inst-1-895807196.dzn", "status": "ok", "score": -1, "results": {"main": {"runs": [{"seed": None, "status": "C", "time": 0.37091660499572754, "extra": {"objs": [], "flattenStatus": "ok", "flattenTime": 0.1721, "instanceType": "unsat", "answerStatus": "unknown"}}]}, "oracle": {"runs": []}}}, "status": "ok", "score": -1}
{"totalTime": 1.6420838832855225, "genResults": {"instance": "gen-inst-1.param", "status": "sat", "seed": 930112402, "SRTime": 0, "solverTime": 0.11004495620727539}, "instanceResults": {"instance": "./detailed-output/inst-1-930112402.dzn", "status": "ok", "score": -1, "results": {"main": {"runs": [{"seed": None, "status": "C", "time": 0.37834668159484863, "extra": {"objs": [], "flattenStatus": "ok", "flattenTime": 0.167752, "instanceType": "unsat", "answerStatus": "unknown"}}]}, "oracle": {"runs": []}}}, "status": "ok", "score": -1}
{"totalTime": 1.640599250793457, "genResults": {"instance": "gen-inst-10.param", "status": "sat", "seed": 1047895682, "SRTime": 0, "solverTime": 0.11404585838317871}, "instanceResults": {"instance": "./detailed-output/inst-10-1047895682.dzn", "status": "ok", "score": -1, "results": {"main": {"runs": [{"seed": None, "status": "C", "time": 0.3735980987548828, "extra": {"objs": [], "flattenStatus": "ok", "flattenTime": 0.169338, "instanceType": "unsat", "answerStatus": "unknown"}}]}, "oracle": {"runs": []}}}, "status": "ok", "score": -1}
{"totalTime": 1.6429524421691895, "genResults": {"instance": "gen-inst-10.param", "status": "sat", "seed": 1430553564, "SRTime": 0, "solverTime": 0.11142897605895996}, "instanceResults": {"instance": "./detailed-output/inst-10-1430553564.dzn", "status": "ok", "score": -1, "results": {"main": {"runs": [{"seed": None, "status": "C", "time": 0.38077497482299805, "extra": {"objs": [], "flattenStatus": "ok", "flattenTime": 0.170269, "instanceType": "unsat", "answerStatus": "unknown"}}]}, "oracle": {"runs": []}}}, "status": "ok", "score": -1}
{"totalTime": 1.669435739517212, "genResults": {"instance": "gen-inst-10.param", "status": "sat", "seed": 1828174830, "SRTime": 0, "solverTime": 0.11997127532958984}, "instanceResults": {"instance": "./detailed-output/inst-10-1828174830.dzn", "status": "ok", "score": -1, "results": {"main": {"runs": [{"seed": None, "status": "C", "time": 0.3727259635925293, "extra": {"objs": [], "flattenStatus": "ok", "flattenTime": 0.172297, "instanceType": "unsat", "answerStatus": "unknown"}}]}, "oracle": {"runs": []}}}, "status": "ok", "score": -1}
{"totalTime": 1.6618776321411133, "genResults": {"instance": "gen-inst-10.param", "status": "sat", "seed": 542193560, "SRTime": 0, "solverTime": 0.11892151832580566}, "instanceResults": {"instance": "./detailed-output/inst-10-542193560.dzn", "status": "ok", "score": -1, "results": {"main": {"runs": [{"seed": None, "status": "C", "time": 0.37842249870300293, "extra": {"objs": [], "flattenStatus": "ok", "flattenTime": 0.169003, "instanceType": "unsat", "answerStatus": "unknown"}}]}, "oracle": {"runs": []}}}, "status": "ok", "score": -1}
{"totalTime": 2.830307722091675, "genResults": {"instance": "gen-inst-10.param", "status": "sat", "seed": 719061008, "SRTime": 0.8307642936706543, "solverTime": 0.08600950241088867}, "instanceResults": {"instance": "./detailed-output/inst-10-719061008.dzn", "status": "ok", "score": -1, "results": {"main": {"runs": [{"seed": None, "status": "C", "time": 0.3712184429168701, "extra": {"objs": [], "flattenStatus": "ok", "flattenTime": 0.172088, "instanceType": "unsat", "answerStatus": "unknown"}}]}, "oracle": {"runs": []}}}, "status": "ok", "score": -1}
{"totalTime": 1.7210421562194824, "genResults": {"instance": "gen-inst-10.param", "status": "sat", "seed": 895807196, "SRTime": 0, "solverTime": 0.12907719612121582}, "instanceResults": {"instance": "./detailed-output/inst-10-895807196.dzn", "status": "ok", "score": -1, "results": {"main": {"runs": [{"seed": None, "status": "C", "time": 0.371715784072876, "extra": {"objs": [], "flattenStatus": "ok", "flattenTime": 0.171207, "instanceType": "unsat", "answerStatus": "unknown"}}]}, "oracle": {"runs": []}}}, "status": "ok", "score": -1}
{"totalTime": 1.65321683883667, "genResults": {"instance": "gen-inst-11.param", "status": "sat", "seed": 1047895682, "SRTime": 0, "solverTime": 0.11088323593139648}, "instanceResults": {"instance": "./detailed-output/inst-11-1047895682.dzn", "status": "ok", "score": -1, "results": {"main": {"runs": [{"seed": None, "status": "C", "time": 0.3804280757904053, "extra": {"objs": [], "flattenStatus": "ok", "flattenTime": 0.167689, "instanceType": "unsat", "answerStatus": "unknown"}}]}, "oracle": {"runs": []}}}, "status": "ok", "score": -1}
{"totalTime": 1.633274793624878, "genResults": {"instance": "gen-inst-11.param", "status": "sat", "seed": 1430553564, "SRTime": 0, "solverTime": 0.11109018325805664}, "instanceResults": {"instance": "./detailed-output/inst-11-1430553564.dzn", "status": "ok", "score": -1, "results": {"main": {"runs": [{"seed": None, "status": "C", "time": 0.37677550315856934, "extra": {"objs": [], "flattenStatus": "ok", "flattenTime": 0.167336, "instanceType": "unsat", "answerStatus": "unknown"}}]}, "oracle": {"runs": []}}}, "status": "ok", "score": -1}
{"totalTime": 1.660365343093872, "genResults": {"instance": "gen-inst-11.param", "status": "sat", "seed": 1828174830, "SRTime": 0, "solverTime": 0.11614418029785156}, "instanceResults": {"instance": "./detailed-output/inst-11-1828174830.dzn", "status": "ok", "score": -1, "results": {"main": {"runs": [{"seed": None, "status": "C", "time": 0.3686394691467285, "extra": {"objs": [], "flattenStatus": "ok", "flattenTime": 0.164818, "instanceType": "unsat", "answerStatus": "unknown"}}]}, "oracle": {"runs": []}}}, "status": "ok", "score": -1}
{"totalTime": 1.6500499248504639, "genResults": {"instance": "gen-inst-11.param", "status": "sat", "seed": 542193560, "SRTime": 0, "solverTime": 0.11736273765563965}, "instanceResults": {"instance": "./detailed-output/inst-11-542193560.dzn", "status": "ok", "score": -1, "results": {"main": {"runs": [{"seed": None, "status": "C", "time": 0.37955379486083984, "extra": {"objs": [], "flattenStatus": "ok", "flattenTime": 0.167878, "instanceType": "unsat", "answerStatus": "unknown"}}]}, "oracle": {"runs": []}}}, "status": "ok", "score": -1}
{"totalTime": 2.8273379802703857, "genResults": {"instance": "gen-inst-11.param", "status": "sat", "seed": 719061008, "SRTime": 0.8309695720672607, "solverTime": 0.08451437950134277}, "instanceResults": {"instance": "./detailed-output/inst-11-719061008.dzn", "status": "ok", "score": -1, "results": {"main": {"runs": [{"seed": None, "status": "C", "time": 0.37070727348327637, "extra": {"objs": [], "flattenStatus": "ok", "flattenTime": 0.172796, "instanceType": "unsat", "answerStatus": "unknown"}}]}, "oracle": {"runs": []}}}, "status": "ok", "score": -1}
{"totalTime": 1.691617488861084, "genResults": {"instance": "gen-inst-11.param", "status": "sat", "seed": 895807196, "SRTime": 0, "solverTime": 0.12823104858398438}, "instanceResults": {"instance": "./detailed-output/inst-11-895807196.dzn", "status": "ok", "score": -1, "results": {"main": {"runs": [{"seed": None, "status": "C", "time": 0.3726034164428711, "extra": {"objs": [], "flattenStatus": "ok", "flattenTime": 0.174051, "instanceType": "unsat", "answerStatus": "unknown"}}]}, "oracle": {"runs": []}}}, "status": "ok", "score": -1}
{"totalTime": 1.6376094818115234, "genResults": {"instance": "gen-inst-12.param", "status": "sat", "seed": 1047895682, "SRTime": 0, "solverTime": 0.1139528751373291}, "instanceResults": {"instance": "./detailed-output/inst-12-1047895682.dzn", "status": "ok", "score": -1, "results": {"main": {"runs": [{"seed": None, "status": "C", "time": 0.37581539154052734, "extra": {"objs": [], "flattenStatus": "ok", "flattenTime": 0.17061, "instanceType": "unsat", "answerStatus": "unknown"}}]}, "oracle": {"runs": []}}}, "status": "ok", "score": -1}
{"totalTime": 1.6437432765960693, "genResults": {"instance": "gen-inst-12.param", "status": "sat", "seed": 1430553564, "SRTime": 0, "solverTime": 0.1132817268371582}, "instanceResults": {"instance": "./detailed-output/inst-12-1430553564.dzn", "status": "ok", "score": -1, "results": {"main": {"runs": [{"seed": None, "status": "C", "time": 0.37157750129699707, "extra": {"objs": [], "flattenStatus": "ok", "flattenTime": 0.169561, "instanceType": "unsat", "answerStatus": "unknown"}}]}, "oracle": {"runs": []}}}, "status": "ok", "score": -1}
{"totalTime": 1.6677370071411133, "genResults": {"instance": "gen-inst-12.param", "status": "sat", "seed": 1828174830, "SRTime": 0, "solverTime": 0.1167762279510498}, "instanceResults": {"instance": "./detailed-output/inst-12-1828174830.dzn", "status": "ok", "score": -1, "results": {"main": {"runs": [{"seed": None, "status": "C", "time": 0.37001633644104004, "extra": {"objs": [], "flattenStatus": "ok", "flattenTime": 0.172511, "instanceType": "unsat", "answerStatus": "unknown"}}]}, "oracle": {"runs": []}}}, "status": "ok", "score": -1}
{"totalTime": 1.6602826118469238, "genResults": {"instance": "gen-inst-12.param", "status": "sat", "seed": 542193560, "SRTime": 0, "solverTime": 0.10919475555419922}, "instanceResults": {"instance": "./detailed-output/inst-12-542193560.dzn", "status": "ok", "score": -1, "results": {"main": {"runs": [{"seed": None, "status": "C", "time": 0.3788793087005615, "extra": {"objs": [], "flattenStatus": "ok", "flattenTime": 0.169636, "instanceType": "unsat", "answerStatus": "unknown"}}]}, "oracle": {"runs": []}}}, "status": "ok", "score": -1}
{"totalTime": 2.8105432987213135, "genResults": {"instance": "gen-inst-12.param", "status": "sat", "seed": 719061008, "SRTime": 0.8142490386962891, "solverTime": 0.08638906478881836}, "instanceResults": {"instance": "./detailed-output/inst-12-719061008.dzn", "status": "ok", "score": -1, "results": {"main": {"runs": [{"seed": None, "status": "C", "time": 0.3695530891418457, "extra": {"objs": [], "flattenStatus": "ok", "flattenTime": 0.17799, "instanceType": "unsat", "answerStatus": "unknown"}}]}, "oracle": {"runs": []}}}, "status": "ok", "score": -1}
{"totalTime": 1.676351547241211, "genResults": {"instance": "gen-inst-12.param", "status": "sat", "seed": 895807196, "SRTime": 0, "solverTime": 0.12178921699523926}, "instanceResults": {"instance": "./detailed-output/inst-12-895807196.dzn", "status": "ok", "score": -1, "results": {"main": {"runs": [{"seed": None, "status": "C", "time": 0.3787045478820801, "extra": {"objs": [], "flattenStatus": "ok", "flattenTime": 0.169284, "instanceType": "unsat", "answerStatus": "unknown"}}]}, "oracle": {"runs": []}}}, "status": "ok", "score": -1}
{"totalTime": 1.6560084819793701, "genResults": {"instance": "gen-inst-13.param", "status": "sat", "seed": 1047895682, "SRTime": 0, "solverTime": 0.12031984329223633}, "instanceResults": {"instance": "./detailed-output/inst-13-1047895682.dzn", "status": "ok", "score": -1, "results": {"main": {"runs": [{"seed": None, "status": "C", "time": 0.3771374225616455, "extra": {"objs": [], "flattenStatus": "ok", "flattenTime": 0.168984, "instanceType": "unsat", "answerStatus": "unknown"}}]}, "oracle": {"runs": []}}}, "status": "ok", "score": -1}
{"totalTime": 1.6345772743225098, "genResults": {"instance": "gen-inst-13.param", "status": "sat", "seed": 1430553564, "SRTime": 0, "solverTime": 0.10836219787597656}, "instanceResults": {"instance": "./detailed-output/inst-13-1430553564.dzn", "status": "ok", "score": -1, "results": {"main": {"runs": [{"seed": None, "status": "C", "time": 0.37752556800842285, "extra": {"objs": [], "flattenStatus": "ok", "flattenTime": 0.169031, "instanceType": "unsat", "answerStatus": "unknown"}}]}, "oracle": {"runs": []}}}, "status": "ok", "score": -1}
{"totalTime": 1.698148488998413, "genResults": {"instance": "gen-inst-13.param", "status": "sat", "seed": 1828174830, "SRTime": 0, "solverTime": 0.1194908618927002}, "instanceResults": {"instance": "./detailed-output/inst-13-1828174830.dzn", "status": "ok", "score": -1, "results": {"main": {"runs": [{"seed": None, "status": "C", "time": 0.38098883628845215, "extra": {"objs": [], "flattenStatus": "ok", "flattenTime": 0.169473, "instanceType": "unsat", "answerStatus": "unknown"}}]}, "oracle": {"runs": []}}}, "status": "ok", "score": -1}
{"totalTime": 1.6566050052642822, "genResults": {"instance": "gen-inst-13.param", "status": "sat", "seed": 542193560, "SRTime": 0, "solverTime": 0.11742520332336426}, "instanceResults": {"instance": "./detailed-output/inst-13-542193560.dzn", "status": "ok", "score": -1, "results": {"main": {"runs": [{"seed": None, "status": "C", "time": 0.37881994247436523, "extra": {"objs": [], "flattenStatus": "ok", "flattenTime": 0.169576, "instanceType": "unsat", "answerStatus": "unknown"}}]}, "oracle": {"runs": []}}}, "status": "ok", "score": -1}
{"totalTime": 2.7990643978118896, "genResults": {"instance": "gen-inst-13.param", "status": "sat", "seed": 719061008, "SRTime": 0.8086435794830322, "solverTime": 0.0845036506652832}, "instanceResults": {"instance": "./detailed-output/inst-13-719061008.dzn", "status": "ok", "score": -1, "results": {"main": {"runs": [{"seed": None, "status": "C", "time": 0.37199878692626953, "extra": {"objs": [], "flattenStatus": "ok", "flattenTime": 0.170414, "instanceType": "unsat", "answerStatus": "unknown"}}]}, "oracle": {"runs": []}}}, "status": "ok", "score": -1}
{"totalTime": 1.6685030460357666, "genResults": {"instance": "gen-inst-13.param", "status": "sat", "seed": 895807196, "SRTime": 0, "solverTime": 0.11581993103027344}, "instanceResults": {"instance": "./detailed-output/inst-13-895807196.dzn", "status": "ok", "score": -1, "results": {"main": {"runs": [{"seed": None, "status": "C", "time": 0.372478723526001, "extra": {"objs": [], "flattenStatus": "ok", "flattenTime": 0.170919, "instanceType": "unsat", "answerStatus": "unknown"}}]}, "oracle": {"runs": []}}}, "status": "ok", "score": -1}
{"totalTime": 1.6403791904449463, "genResults": {"instance": "gen-inst-14.param", "status": "sat", "seed": 1047895682, "SRTime": 0, "solverTime": 0.1108851432800293}, "instanceResults": {"instance": "./detailed-output/inst-14-1047895682.dzn", "status": "ok", "score": -1, "results": {"main": {"runs": [{"seed": None, "status": "C", "time": 0.37467050552368164, "extra": {"objs": [], "flattenStatus": "ok", "flattenTime": 0.168695, "instanceType": "unsat", "answerStatus": "unknown"}}]}, "oracle": {"runs": []}}}, "status": "ok", "score": -1}
{"totalTime": 1.6550602912902832, "genResults": {"instance": "gen-inst-14.param", "status": "sat", "seed": 1430553564, "SRTime": 0, "solverTime": 0.11883783340454102}, "instanceResults": {"instance": "./detailed-output/inst-14-1430553564.dzn", "status": "ok", "score": -1, "results": {"main": {"runs": [{"seed": None, "status": "C", "time": 0.3787517547607422, "extra": {"objs": [], "flattenStatus": "ok", "flattenTime": 0.16925, "instanceType": "unsat", "answerStatus": "unknown"}}]}, "oracle": {"runs": []}}}, "status": "ok", "score": -1}
{"totalTime": 1.657459020614624, "genResults": {"instance": "gen-inst-14.param", "status": "sat", "seed": 1828174830, "SRTime": 0, "solverTime": 0.11274194717407227}, "instanceResults": {"instance": "./detailed-output/inst-14-1828174830.dzn", "status": "ok", "score": -1, "results": {"main": {"runs": [{"seed": None, "status": "C", "time": 0.3719637393951416, "extra": {"objs": [], "flattenStatus": "ok", "flattenTime": 0.168089, "instanceType": "unsat", "answerStatus": "unknown"}}]}, "oracle": {"runs": []}}}, "status": "ok", "score": -1}
{"totalTime": 1.6536953449249268, "genResults": {"instance": "gen-inst-14.param", "status": "sat", "seed": 542193560, "SRTime": 0, "solverTime": 0.11118483543395996}, "instanceResults": {"instance": "./detailed-output/inst-14-542193560.dzn", "status": "ok", "score": -1, "results": {"main": {"runs": [{"seed": None, "status": "C", "time": 0.3714742660522461, "extra": {"objs": [], "flattenStatus": "ok", "flattenTime": 0.167834, "instanceType": "unsat", "answerStatus": "unknown"}}]}, "oracle": {"runs": []}}}, "status": "ok", "score": -1}
{"totalTime": 2.811784505844116, "genResults": {"instance": "gen-inst-14.param", "status": "sat", "seed": 719061008, "SRTime": 0.8240175247192383, "solverTime": 0.08416223526000977}, "instanceResults": {"instance": "./detailed-output/inst-14-719061008.dzn", "status": "ok", "score": -1, "results": {"main": {"runs": [{"seed": None, "status": "C", "time": 0.3715803623199463, "extra": {"objs": [], "flattenStatus": "ok", "flattenTime": 0.170428, "instanceType": "unsat", "answerStatus": "unknown"}}]}, "oracle": {"runs": []}}}, "status": "ok", "score": -1}
{"totalTime": 2.050977945327759, "genResults": {"instance": "gen-inst-14.param", "status": "sat", "seed": 895807196, "SRTime": 0, "solverTime": 0.12673592567443848}, "instanceResults": {"instance": "./detailed-output/inst-14-895807196.dzn", "status": "ok", "score": -1, "results": {"main": {"runs": [{"seed": None, "status": "C", "time": 0.36943626403808594, "extra": {"objs": [], "flattenStatus": "ok", "flattenTime": 0.176115, "instanceType": "unsat", "answerStatus": "unknown"}}]}, "oracle": {"runs": []}}}, "status": "ok", "score": -1}
{"totalTime": 1.65081787109375, "genResults": {"instance": "gen-inst-15.param", "status": "sat", "seed": 1047895682, "SRTime": 0, "solverTime": 0.11303281784057617}, "instanceResults": {"instance": "./detailed-output/inst-15-1047895682.dzn", "status": "ok", "score": -1, "results": {"main": {"runs": [{"seed": None, "status": "C", "time": 0.3784313201904297, "extra": {"objs": [], "flattenStatus": "ok", "flattenTime": 0.167596, "instanceType": "unsat", "answerStatus": "unknown"}}]}, "oracle": {"runs": []}}}, "status": "ok", "score": -1}
{"totalTime": 1.6621379852294922, "genResults": {"instance": "gen-inst-15.param", "status": "sat", "seed": 1430553564, "SRTime": 0, "solverTime": 0.11771631240844727}, "instanceResults": {"instance": "./detailed-output/inst-15-1430553564.dzn", "status": "ok", "score": -1, "results": {"main": {"runs": [{"seed": None, "status": "C", "time": 0.37485790252685547, "extra": {"objs": [], "flattenStatus": "ok", "flattenTime": 0.170671, "instanceType": "unsat", "answerStatus": "unknown"}}]}, "oracle": {"runs": []}}}, "status": "ok", "score": -1}
{"totalTime": 1.6499896049499512, "genResults": {"instance": "gen-inst-15.param", "status": "sat", "seed": 1828174830, "SRTime": 0, "solverTime": 0.11123156547546387}, "instanceResults": {"instance": "./detailed-output/inst-15-1828174830.dzn", "status": "ok", "score": -1, "results": {"main": {"runs": [{"seed": None, "status": "C", "time": 0.3731272220611572, "extra": {"objs": [], "flattenStatus": "ok", "flattenTime": 0.170249, "instanceType": "unsat", "answerStatus": "unknown"}}]}, "oracle": {"runs": []}}}, "status": "ok", "score": -1}
{"totalTime": 1.6448798179626465, "genResults": {"instance": "gen-inst-15.param", "status": "sat", "seed": 542193560, "SRTime": 0, "solverTime": 0.10934138298034668}, "instanceResults": {"instance": "./detailed-output/inst-15-542193560.dzn", "status": "ok", "score": -1, "results": {"main": {"runs": [{"seed": None, "status": "C", "time": 0.36661791801452637, "extra": {"objs": [], "flattenStatus": "ok", "flattenTime": 0.168985, "instanceType": "unsat", "answerStatus": "unknown"}}]}, "oracle": {"runs": []}}}, "status": "ok", "score": -1}
{"totalTime": 2.849552869796753, "genResults": {"instance": "gen-inst-15.param", "status": "sat", "seed": 719061008, "SRTime": 0.8342525959014893, "solverTime": 0.08628702163696289}, "instanceResults": {"instance": "./detailed-output/inst-15-719061008.dzn", "status": "ok", "score": -1, "results": {"main": {"runs": [{"seed": None, "status": "C", "time": 0.36684465408325195, "extra": {"objs": [], "flattenStatus": "ok", "flattenTime": 0.170228, "instanceType": "unsat", "answerStatus": "unknown"}}]}, "oracle": {"runs": []}}}, "status": "ok", "score": -1}
{"totalTime": 1.6740646362304688, "genResults": {"instance": "gen-inst-15.param", "status": "sat", "seed": 895807196, "SRTime": 0, "solverTime": 0.11761069297790527}, "instanceResults": {"instance": "./detailed-output/inst-15-895807196.dzn", "status": "ok", "score": -1, "results": {"main": {"runs": [{"seed": None, "status": "C", "time": 0.37164902687072754, "extra": {"objs": [], "flattenStatus": "ok", "flattenTime": 0.1729, "instanceType": "unsat", "answerStatus": "unknown"}}]}, "oracle": {"runs": []}}}, "status": "ok", "score": -1}
{"totalTime": 1.6456921100616455, "genResults": {"instance": "gen-inst-16.param", "status": "sat", "seed": 1047895682, "SRTime": 0, "solverTime": 0.11395740509033203}, "instanceResults": {"instance": "./detailed-output/inst-16-1047895682.dzn", "status": "ok", "score": -1, "results": {"main": {"runs": [{"seed": None, "status": "C", "time": 0.373746395111084, "extra": {"objs": [], "flattenStatus": "ok", "flattenTime": 0.171, "instanceType": "unsat", "answerStatus": "unknown"}}]}, "oracle": {"runs": []}}}, "status": "ok", "score": -1}
{"totalTime": 1.6463384628295898, "genResults": {"instance": "gen-inst-16.param", "status": "sat", "seed": 1430553564, "SRTime": 0, "solverTime": 0.11200141906738281}, "instanceResults": {"instance": "./detailed-output/inst-16-1430553564.dzn", "status": "ok", "score": -1, "results": {"main": {"runs": [{"seed": None, "status": "C", "time": 0.3822166919708252, "extra": {"objs": [], "flattenStatus": "ok", "flattenTime": 0.169075, "instanceType": "unsat", "answerStatus": "unknown"}}]}, "oracle": {"runs": []}}}, "status": "ok", "score": -1}
{"totalTime": 1.646721601486206, "genResults": {"instance": "gen-inst-16.param", "status": "sat", "seed": 1828174830, "SRTime": 0, "solverTime": 0.10814595222473145}, "instanceResults": {"instance": "./detailed-output/inst-16-1828174830.dzn", "status": "ok", "score": -1, "results": {"main": {"runs": [{"seed": None, "status": "C", "time": 0.3786017894744873, "extra": {"objs": [], "flattenStatus": "ok", "flattenTime": 0.168552, "instanceType": "unsat", "answerStatus": "unknown"}}]}, "oracle": {"runs": []}}}, "status": "ok", "score": -1}
{"totalTime": 1.6612420082092285, "genResults": {"instance": "gen-inst-16.param", "status": "sat", "seed": 542193560, "SRTime": 0, "solverTime": 0.11556172370910645}, "instanceResults": {"instance": "./detailed-output/inst-16-542193560.dzn", "status": "ok", "score": -1, "results": {"main": {"runs": [{"seed": None, "status": "C", "time": 0.3744466304779053, "extra": {"objs": [], "flattenStatus": "ok", "flattenTime": 0.170377, "instanceType": "unsat", "answerStatus": "unknown"}}]}, "oracle": {"runs": []}}}, "status": "ok", "score": -1}
{"totalTime": 1.6472046375274658, "genResults": {"instance": "gen-inst-16.param", "status": "sat", "seed": 719061008, "SRTime": 0, "solverTime": 0.11944746971130371}, "instanceResults": {"instance": "./detailed-output/inst-16-719061008.dzn", "status": "ok", "score": -1, "results": {"main": {"runs": [{"seed": None, "status": "C", "time": 0.37381482124328613, "extra": {"objs": [], "flattenStatus": "ok", "flattenTime": 0.168491, "instanceType": "unsat", "answerStatus": "unknown"}}]}, "oracle": {"runs": []}}}, "status": "ok", "score": -1}
{"totalTime": 1.6361174583435059, "genResults": {"instance": "gen-inst-16.param", "status": "sat", "seed": 895807196, "SRTime": 0, "solverTime": 0.11103129386901855}, "instanceResults": {"instance": "./detailed-output/inst-16-895807196.dzn", "status": "ok", "score": -1, "results": {"main": {"runs": [{"seed": None, "status": "C", "time": 0.3780026435852051, "extra": {"objs": [], "flattenStatus": "ok", "flattenTime": 0.168382, "instanceType": "unsat", "answerStatus": "unknown"}}]}, "oracle": {"runs": []}}}, "status": "ok", "score": -1}
{"totalTime": 2.8027589321136475, "genResults": {"instance": "gen-inst-16.param", "status": "sat", "seed": 930112402, "SRTime": 0.8319680690765381, "solverTime": 0.08380532264709473}, "instanceResults": {"instance": "./detailed-output/inst-16-930112402.dzn", "status": "ok", "score": -1, "results": {"main": {"runs": [{"seed": None, "status": "C", "time": 0.3785519599914551, "extra": {"objs": [], "flattenStatus": "ok", "flattenTime": 0.167681, "instanceType": "unsat", "answerStatus": "unknown"}}]}, "oracle": {"runs": []}}}, "status": "ok", "score": -1}
{"totalTime": 1.6589305400848389, "genResults": {"instance": "gen-inst-17.param", "status": "sat", "seed": 1047895682, "SRTime": 0, "solverTime": 0.1188046932220459}, "instanceResults": {"instance": "./detailed-output/inst-17-1047895682.dzn", "status": "ok", "score": -1, "results": {"main": {"runs": [{"seed": None, "status": "C", "time": 0.3673248291015625, "extra": {"objs": [], "flattenStatus": "ok", "flattenTime": 0.170911, "instanceType": "unsat", "answerStatus": "unknown"}}]}, "oracle": {"runs": []}}}, "status": "ok", "score": -1}
{"totalTime": 1.6526849269866943, "genResults": {"instance": "gen-inst-17.param", "status": "sat", "seed": 1430553564, "SRTime": 0, "solverTime": 0.1082155704498291}, "instanceResults": {"instance": "./detailed-output/inst-17-1430553564.dzn", "status": "ok", "score": -1, "results": {"main": {"runs": [{"seed": None, "status": "C", "time": 0.3783121109008789, "extra": {"objs": [], "flattenStatus": "ok", "flattenTime": 0.170413, "instanceType": "unsat", "answerStatus": "unknown"}}]}, "oracle": {"runs": []}}}, "status": "ok", "score": -1}
{"totalTime": 1.6463932991027832, "genResults": {"instance": "gen-inst-17.param", "status": "sat", "seed": 1828174830, "SRTime": 0, "solverTime": 0.1112966537475586}, "instanceResults": {"instance": "./detailed-output/inst-17-1828174830.dzn", "status": "ok", "score": -1, "results": {"main": {"runs": [{"seed": None, "status": "C", "time": 0.36911511421203613, "extra": {"objs": [], "flattenStatus": "ok", "flattenTime": 0.171188, "instanceType": "unsat", "answerStatus": "unknown"}}]}, "oracle": {"runs": []}}}, "status": "ok", "score": -1}
{"totalTime": 1.6445729732513428, "genResults": {"instance": "gen-inst-17.param", "status": "sat", "seed": 542193560, "SRTime": 0, "solverTime": 0.11804723739624023}, "instanceResults": {"instance": "./detailed-output/inst-17-542193560.dzn", "status": "ok", "score": -1, "results": {"main": {"runs": [{"seed": None, "status": "C", "time": 0.36840009689331055, "extra": {"objs": [], "flattenStatus": "ok", "flattenTime": 0.16774, "instanceType": "unsat", "answerStatus": "unknown"}}]}, "oracle": {"runs": []}}}, "status": "ok", "score": -1}
{"totalTime": 1.6388092041015625, "genResults": {"instance": "gen-inst-17.param", "status": "sat", "seed": 719061008, "SRTime": 0, "solverTime": 0.10991644859313965}, "instanceResults": {"instance": "./detailed-output/inst-17-719061008.dzn", "status": "ok", "score": -1, "results": {"main": {"runs": [{"seed": None, "status": "C", "time": 0.3739590644836426, "extra": {"objs": [], "flattenStatus": "ok", "flattenTime": 0.170749, "instanceType": "unsat", "answerStatus": "unknown"}}]}, "oracle": {"runs": []}}}, "status": "ok", "score": -1}
{"totalTime": 1.66135573387146, "genResults": {"instance": "gen-inst-17.param", "status": "sat", "seed": 895807196, "SRTime": 0, "solverTime": 0.12211847305297852}, "instanceResults": {"instance": "./detailed-output/inst-17-895807196.dzn", "status": "ok", "score": -1, "results": {"main": {"runs": [{"seed": None, "status": "C", "time": 0.3635711669921875, "extra": {"objs": [], "flattenStatus": "ok", "flattenTime": 0.1693, "instanceType": "unsat", "answerStatus": "unknown"}}]}, "oracle": {"runs": []}}}, "status": "ok", "score": -1}
{"totalTime": 2.8128840923309326, "genResults": {"instance": "gen-inst-17.param", "status": "sat", "seed": 930112402, "SRTime": 0.8135404586791992, "solverTime": 0.08379316329956055}, "instanceResults": {"instance": "./detailed-output/inst-17-930112402.dzn", "status": "ok", "score": -1, "results": {"main": {"runs": [{"seed": None, "status": "C", "time": 0.3792908191680908, "extra": {"objs": [], "flattenStatus": "ok", "flattenTime": 0.190519, "instanceType": "unsat", "answerStatus": "unknown"}}]}, "oracle": {"runs": []}}}, "status": "ok", "score": -1}
{"totalTime": 1.6532273292541504, "genResults": {"instance": "gen-inst-18.param", "status": "sat", "seed": 1047895682, "SRTime": 0, "solverTime": 0.11398649215698242}, "instanceResults": {"instance": "./detailed-output/inst-18-1047895682.dzn", "status": "ok", "score": -1, "results": {"main": {"runs": [{"seed": None, "status": "C", "time": 0.38082170486450195, "extra": {"objs": [], "flattenStatus": "ok", "flattenTime": 0.168558, "instanceType": "unsat", "answerStatus": "unknown"}}]}, "oracle": {"runs": []}}}, "status": "ok", "score": -1}
{"totalTime": 1.6672825813293457, "genResults": {"instance": "gen-inst-18.param", "status": "sat", "seed": 1430553564, "SRTime": 0, "solverTime": 0.10969233512878418}, "instanceResults": {"instance": "./detailed-output/inst-18-1430553564.dzn", "status": "ok", "score": -1, "results": {"main": {"runs": [{"seed": None, "status": "C", "time": 0.3797180652618408, "extra": {"objs": [], "flattenStatus": "ok", "flattenTime": 0.170126, "instanceType": "unsat", "answerStatus": "unknown"}}]}, "oracle": {"runs": []}}}, "status": "ok", "score": -1}
{"totalTime": 1.6503558158874512, "genResults": {"instance": "gen-inst-18.param", "status": "sat", "seed": 1828174830, "SRTime": 0, "solverTime": 0.11386966705322266}, "instanceResults": {"instance": "./detailed-output/inst-18-1828174830.dzn", "status": "ok", "score": -1, "results": {"main": {"runs": [{"seed": None, "status": "C", "time": 0.37936878204345703, "extra": {"objs": [], "flattenStatus": "ok", "flattenTime": 0.167576, "instanceType": "unsat", "answerStatus": "unknown"}}]}, "oracle": {"runs": []}}}, "status": "ok", "score": -1}
{"totalTime": 1.670140266418457, "genResults": {"instance": "gen-inst-18.param", "status": "sat", "seed": 542193560, "SRTime": 0, "solverTime": 0.11080503463745117}, "instanceResults": {"instance": "./detailed-output/inst-18-542193560.dzn", "status": "ok", "score": -1, "results": {"main": {"runs": [{"seed": None, "status": "C", "time": 0.3707563877105713, "extra": {"objs": [], "flattenStatus": "ok", "flattenTime": 0.168835, "instanceType": "unsat", "answerStatus": "unknown"}}]}, "oracle": {"runs": []}}}, "status": "ok", "score": -1}
{"totalTime": 1.6566290855407715, "genResults": {"instance": "gen-inst-18.param", "status": "sat", "seed": 719061008, "SRTime": 0, "solverTime": 0.11556386947631836}, "instanceResults": {"instance": "./detailed-output/inst-18-719061008.dzn", "status": "ok", "score": -1, "results": {"main": {"runs": [{"seed": None, "status": "C", "time": 0.37129902839660645, "extra": {"objs": [], "flattenStatus": "ok", "flattenTime": 0.169101, "instanceType": "unsat", "answerStatus": "unknown"}}]}, "oracle": {"runs": []}}}, "status": "ok", "score": -1}
{"totalTime": 1.662653923034668, "genResults": {"instance": "gen-inst-18.param", "status": "sat", "seed": 895807196, "SRTime": 0, "solverTime": 0.11737298965454102}, "instanceResults": {"instance": "./detailed-output/inst-18-895807196.dzn", "status": "ok", "score": -1, "results": {"main": {"runs": [{"seed": None, "status": "C", "time": 0.3728656768798828, "extra": {"objs": [], "flattenStatus": "ok", "flattenTime": 0.170349, "instanceType": "unsat", "answerStatus": "unknown"}}]}, "oracle": {"runs": []}}}, "status": "ok", "score": -1}
{"totalTime": 2.8316147327423096, "genResults": {"instance": "gen-inst-18.param", "status": "sat", "seed": 930112402, "SRTime": 0.8517260551452637, "solverTime": 0.08267092704772949}, "instanceResults": {"instance": "./detailed-output/inst-18-930112402.dzn", "status": "ok", "score": -1, "results": {"main": {"runs": [{"seed": None, "status": "C", "time": 0.37791872024536133, "extra": {"objs": [], "flattenStatus": "ok", "flattenTime": 0.168362, "instanceType": "unsat", "answerStatus": "unknown"}}]}, "oracle": {"runs": []}}}, "status": "ok", "score": -1}
{"totalTime": 1.6196141242980957, "genResults": {"instance": "gen-inst-19.param", "status": "sat", "seed": 1047895682, "SRTime": 0, "solverTime": 0.1151285171508789}, "instanceResults": {"instance": "./detailed-output/inst-19-1047895682.dzn", "status": "ok", "score": -1, "results": {"main": {"runs": [{"seed": None, "status": "C", "time": 0.3665034770965576, "extra": {"objs": [], "flattenStatus": "ok", "flattenTime": 0.171632, "instanceType": "unsat", "answerStatus": "unknown"}}]}, "oracle": {"runs": []}}}, "status": "ok", "score": -1}
{"totalTime": 1.6455934047698975, "genResults": {"instance": "gen-inst-19.param", "status": "sat", "seed": 1430553564, "SRTime": 0, "solverTime": 0.1144707202911377}, "instanceResults": {"instance": "./detailed-output/inst-19-1430553564.dzn", "status": "ok", "score": -1, "results": {"main": {"runs": [{"seed": None, "status": "C", "time": 0.37200284004211426, "extra": {"objs": [], "flattenStatus": "ok", "flattenTime": 0.169575, "instanceType": "unsat", "answerStatus": "unknown"}}]}, "oracle": {"runs": []}}}, "status": "ok", "score": -1}
{"totalTime": 1.634106159210205, "genResults": {"instance": "gen-inst-19.param", "status": "sat", "seed": 1828174830, "SRTime": 0, "solverTime": 0.11513233184814453}, "instanceResults": {"instance": "./detailed-output/inst-19-1828174830.dzn", "status": "ok", "score": -1, "results": {"main": {"runs": [{"seed": None, "status": "C", "time": 0.37001633644104004, "extra": {"objs": [], "flattenStatus": "ok", "flattenTime": 0.168091, "instanceType": "unsat", "answerStatus": "unknown"}}]}, "oracle": {"runs": []}}}, "status": "ok", "score": -1}
{"totalTime": 1.7283744812011719, "genResults": {"instance": "gen-inst-19.param", "status": "sat", "seed": 542193560, "SRTime": 0, "solverTime": 0.16879010200500488}, "instanceResults": {"instance": "./detailed-output/inst-19-542193560.dzn", "status": "ok", "score": -1, "results": {"main": {"runs": [{"seed": None, "status": "C", "time": 0.3780062198638916, "extra": {"objs": [], "flattenStatus": "ok", "flattenTime": 0.167823, "instanceType": "unsat", "answerStatus": "unknown"}}]}, "oracle": {"runs": []}}}, "status": "ok", "score": -1}
{"totalTime": 1.663386583328247, "genResults": {"instance": "gen-inst-19.param", "status": "sat", "seed": 719061008, "SRTime": 0, "solverTime": 0.11755943298339844}, "instanceResults": {"instance": "./detailed-output/inst-19-719061008.dzn", "status": "ok", "score": -1, "results": {"main": {"runs": [{"seed": None, "status": "C", "time": 0.37935495376586914, "extra": {"objs": [], "flattenStatus": "ok", "flattenTime": 0.17104, "instanceType": "unsat", "answerStatus": "unknown"}}]}, "oracle": {"runs": []}}}, "status": "ok", "score": -1}
{"totalTime": 1.6392583847045898, "genResults": {"instance": "gen-inst-19.param", "status": "sat", "seed": 895807196, "SRTime": 0, "solverTime": 0.1183478832244873}, "instanceResults": {"instance": "./detailed-output/inst-19-895807196.dzn", "status": "ok", "score": -1, "results": {"main": {"runs": [{"seed": None, "status": "C", "time": 0.3781318664550781, "extra": {"objs": [], "flattenStatus": "ok", "flattenTime": 0.168459, "instanceType": "unsat", "answerStatus": "unknown"}}]}, "oracle": {"runs": []}}}, "status": "ok", "score": -1}
{"totalTime": 2.7808563709259033, "genResults": {"instance": "gen-inst-19.param", "status": "sat", "seed": 930112402, "SRTime": 0.8084304332733154, "solverTime": 0.08488607406616211}, "instanceResults": {"instance": "./detailed-output/inst-19-930112402.dzn", "status": "ok", "score": -1, "results": {"main": {"runs": [{"seed": None, "status": "C", "time": 0.3727707862854004, "extra": {"objs": [], "flattenStatus": "ok", "flattenTime": 0.169765, "instanceType": "unsat", "answerStatus": "unknown"}}]}, "oracle": {"runs": []}}}, "status": "ok", "score": -1}
{"totalTime": 1.6556286811828613, "genResults": {"instance": "gen-inst-2.param", "status": "sat", "seed": 1047895682, "SRTime": 0, "solverTime": 0.10954451560974121}, "instanceResults": {"instance": "./detailed-output/inst-2-1047895682.dzn", "status": "ok", "score": -1, "results": {"main": {"runs": [{"seed": None, "status": "C", "time": 0.3794393539428711, "extra": {"objs": [], "flattenStatus": "ok", "flattenTime": 0.170542, "instanceType": "unsat", "answerStatus": "unknown"}}]}, "oracle": {"runs": []}}}, "status": "ok", "score": -1}
{"totalTime": 1.6323437690734863, "genResults": {"instance": "gen-inst-2.param", "status": "sat", "seed": 1430553564, "SRTime": 0, "solverTime": 0.10830235481262207}, "instanceResults": {"instance": "./detailed-output/inst-2-1430553564.dzn", "status": "ok", "score": -1, "results": {"main": {"runs": [{"seed": None, "status": "C", "time": 0.36722874641418457, "extra": {"objs": [], "flattenStatus": "ok", "flattenTime": 0.171239, "instanceType": "unsat", "answerStatus": "unknown"}}]}, "oracle": {"runs": []}}}, "status": "ok", "score": -1}
{"totalTime": 1.6479084491729736, "genResults": {"instance": "gen-inst-2.param", "status": "sat", "seed": 1828174830, "SRTime": 0, "solverTime": 0.1098625659942627}, "instanceResults": {"instance": "./detailed-output/inst-2-1828174830.dzn", "status": "ok", "score": -1, "results": {"main": {"runs": [{"seed": None, "status": "C", "time": 0.37773942947387695, "extra": {"objs": [], "flattenStatus": "ok", "flattenTime": 0.169677, "instanceType": "unsat", "answerStatus": "unknown"}}]}, "oracle": {"runs": []}}}, "status": "ok", "score": -1}
{"totalTime": 1.6394002437591553, "genResults": {"instance": "gen-inst-2.param", "status": "sat", "seed": 542193560, "SRTime": 0, "solverTime": 0.11943387985229492}, "instanceResults": {"instance": "./detailed-output/inst-2-542193560.dzn", "status": "ok", "score": -1, "results": {"main": {"runs": [{"seed": None, "status": "C", "time": 0.37172651290893555, "extra": {"objs": [], "flattenStatus": "ok", "flattenTime": 0.169472, "instanceType": "unsat", "answerStatus": "unknown"}}]}, "oracle": {"runs": []}}}, "status": "ok", "score": -1}
{"totalTime": 2.8056366443634033, "genResults": {"instance": "gen-inst-2.param", "status": "sat", "seed": 719061008, "SRTime": 0.8203015327453613, "solverTime": 0.08477497100830078}, "instanceResults": {"instance": "./detailed-output/inst-2-719061008.dzn", "status": "ok", "score": -1, "results": {"main": {"runs": [{"seed": None, "status": "C", "time": 0.37139320373535156, "extra": {"objs": [], "flattenStatus": "ok", "flattenTime": 0.173968, "instanceType": "unsat", "answerStatus": "unknown"}}]}, "oracle": {"runs": []}}}, "status": "ok", "score": -1}
{"totalTime": 1.675224781036377, "genResults": {"instance": "gen-inst-2.param", "status": "sat", "seed": 895807196, "SRTime": 0, "solverTime": 0.12248682975769043}, "instanceResults": {"instance": "./detailed-output/inst-2-895807196.dzn", "status": "ok", "score": -1, "results": {"main": {"runs": [{"seed": None, "status": "C", "time": 0.3710646629333496, "extra": {"objs": [], "flattenStatus": "ok", "flattenTime": 0.170842, "instanceType": "unsat", "answerStatus": "unknown"}}]}, "oracle": {"runs": []}}}, "status": "ok", "score": -1}
{"totalTime": 1.6414830684661865, "genResults": {"instance": "gen-inst-2.param", "status": "sat", "seed": 930112402, "SRTime": 0, "solverTime": 0.11427927017211914}, "instanceResults": {"instance": "./detailed-output/inst-2-930112402.dzn", "status": "ok", "score": -1, "results": {"main": {"runs": [{"seed": None, "status": "C", "time": 0.3700590133666992, "extra": {"objs": [], "flattenStatus": "ok", "flattenTime": 0.167149, "instanceType": "unsat", "answerStatus": "unknown"}}]}, "oracle": {"runs": []}}}, "status": "ok", "score": -1}
{"totalTime": 1.6379411220550537, "genResults": {"instance": "gen-inst-20.param", "status": "sat", "seed": 1047895682, "SRTime": 0, "solverTime": 0.10951113700866699}, "instanceResults": {"instance": "./detailed-output/inst-20-1047895682.dzn", "status": "ok", "score": -1, "results": {"main": {"runs": [{"seed": None, "status": "C", "time": 0.3784005641937256, "extra": {"objs": [], "flattenStatus": "ok", "flattenTime": 0.16836, "instanceType": "unsat", "answerStatus": "unknown"}}]}, "oracle": {"runs": []}}}, "status": "ok", "score": -1}
{"totalTime": 1.6515045166015625, "genResults": {"instance": "gen-inst-20.param", "status": "sat", "seed": 1430553564, "SRTime": 0, "solverTime": 0.11138629913330078}, "instanceResults": {"instance": "./detailed-output/inst-20-1430553564.dzn", "status": "ok", "score": -1, "results": {"main": {"runs": [{"seed": None, "status": "C", "time": 0.37833523750305176, "extra": {"objs": [], "flattenStatus": "ok", "flattenTime": 0.170249, "instanceType": "unsat", "answerStatus": "unknown"}}]}, "oracle": {"runs": []}}}, "status": "ok", "score": -1}
{"totalTime": 1.6677682399749756, "genResults": {"instance": "gen-inst-20.param", "status": "sat", "seed": 1828174830, "SRTime": 0, "solverTime": 0.11781430244445801}, "instanceResults": {"instance": "./detailed-output/inst-20-1828174830.dzn", "status": "ok", "score": -1, "results": {"main": {"runs": [{"seed": None, "status": "C", "time": 0.379122257232666, "extra": {"objs": [], "flattenStatus": "ok", "flattenTime": 0.168367, "instanceType": "unsat", "answerStatus": "unknown"}}]}, "oracle": {"runs": []}}}, "status": "ok", "score": -1}
{"totalTime": 1.6357996463775635, "genResults": {"instance": "gen-inst-20.param", "status": "sat", "seed": 542193560, "SRTime": 0, "solverTime": 0.1147153377532959}, "instanceResults": {"instance": "./detailed-output/inst-20-542193560.dzn", "status": "ok", "score": -1, "results": {"main": {"runs": [{"seed": None, "status": "C", "time": 0.3730945587158203, "extra": {"objs": [], "flattenStatus": "ok", "flattenTime": 0.168124, "instanceType": "unsat", "answerStatus": "unknown"}}]}, "oracle": {"runs": []}}}, "status": "ok", "score": -1}
{"totalTime": 1.689621925354004, "genResults": {"instance": "gen-inst-20.param", "status": "sat", "seed": 719061008, "SRTime": 0, "solverTime": 0.11123132705688477}, "instanceResults": {"instance": "./detailed-output/inst-20-719061008.dzn", "status": "ok", "score": -1, "results": {"main": {"runs": [{"seed": None, "status": "C", "time": 0.3793635368347168, "extra": {"objs": [], "flattenStatus": "ok", "flattenTime": 0.168407, "instanceType": "unsat", "answerStatus": "unknown"}}]}, "oracle": {"runs": []}}}, "status": "ok", "score": -1}
{"totalTime": 1.6425957679748535, "genResults": {"instance": "gen-inst-20.param", "status": "sat", "seed": 895807196, "SRTime": 0, "solverTime": 0.11116361618041992}, "instanceResults": {"instance": "./detailed-output/inst-20-895807196.dzn", "status": "ok", "score": -1, "results": {"main": {"runs": [{"seed": None, "status": "C", "time": 0.3790011405944824, "extra": {"objs": [], "flattenStatus": "ok", "flattenTime": 0.168578, "instanceType": "unsat", "answerStatus": "unknown"}}]}, "oracle": {"runs": []}}}, "status": "ok", "score": -1}
{"totalTime": 2.782473087310791, "genResults": {"instance": "gen-inst-20.param", "status": "sat", "seed": 930112402, "SRTime": 0.8163719177246094, "solverTime": 0.08436846733093262}, "instanceResults": {"instance": "./detailed-output/inst-20-930112402.dzn", "status": "ok", "score": -1, "results": {"main": {"runs": [{"seed": None, "status": "C", "time": 0.37299036979675293, "extra": {"objs": [], "flattenStatus": "ok", "flattenTime": 0.168032, "instanceType": "unsat", "answerStatus": "unknown"}}]}, "oracle": {"runs": []}}}, "status": "ok", "score": -1}
{"totalTime": 1.6516053676605225, "genResults": {"instance": "gen-inst-21.param", "status": "sat", "seed": 1047895682, "SRTime": 0, "solverTime": 0.1116328239440918}, "instanceResults": {"instance": "./detailed-output/inst-21-1047895682.dzn", "status": "ok", "score": -1, "results": {"main": {"runs": [{"seed": None, "status": "C", "time": 0.3787519931793213, "extra": {"objs": [], "flattenStatus": "ok", "flattenTime": 0.168824, "instanceType": "unsat", "answerStatus": "unknown"}}]}, "oracle": {"runs": []}}}, "status": "ok", "score": -1}
{"totalTime": 1.6732068061828613, "genResults": {"instance": "gen-inst-21.param", "status": "sat", "seed": 1430553564, "SRTime": 0, "solverTime": 0.12114095687866211}, "instanceResults": {"instance": "./detailed-output/inst-21-1430553564.dzn", "status": "ok", "score": -1, "results": {"main": {"runs": [{"seed": None, "status": "C", "time": 0.3782074451446533, "extra": {"objs": [], "flattenStatus": "ok", "flattenTime": 0.168976, "instanceType": "unsat", "answerStatus": "unknown"}}]}, "oracle": {"runs": []}}}, "status": "ok", "score": -1}
{"totalTime": 1.6367535591125488, "genResults": {"instance": "gen-inst-21.param", "status": "sat", "seed": 1828174830, "SRTime": 0, "solverTime": 0.11414241790771484}, "instanceResults": {"instance": "./detailed-output/inst-21-1828174830.dzn", "status": "ok", "score": -1, "results": {"main": {"runs": [{"seed": None, "status": "C", "time": 0.37440943717956543, "extra": {"objs": [], "flattenStatus": "ok", "flattenTime": 0.170002, "instanceType": "unsat", "answerStatus": "unknown"}}]}, "oracle": {"runs": []}}}, "status": "ok", "score": -1}
{"totalTime": 1.6531956195831299, "genResults": {"instance": "gen-inst-21.param", "status": "sat", "seed": 542193560, "SRTime": 0, "solverTime": 0.12549543380737305}, "instanceResults": {"instance": "./detailed-output/inst-21-542193560.dzn", "status": "ok", "score": -1, "results": {"main": {"runs": [{"seed": None, "status": "C", "time": 0.37784552574157715, "extra": {"objs": [], "flattenStatus": "ok", "flattenTime": 0.172474, "instanceType": "unsat", "answerStatus": "unknown"}}]}, "oracle": {"runs": []}}}, "status": "ok", "score": -1}
{"totalTime": 1.6449713706970215, "genResults": {"instance": "gen-inst-21.param", "status": "sat", "seed": 719061008, "SRTime": 0, "solverTime": 0.11774849891662598}, "instanceResults": {"instance": "./detailed-output/inst-21-719061008.dzn", "status": "ok", "score": -1, "results": {"main": {"runs": [{"seed": None, "status": "C", "time": 0.3721628189086914, "extra": {"objs": [], "flattenStatus": "ok", "flattenTime": 0.172692, "instanceType": "unsat", "answerStatus": "unknown"}}]}, "oracle": {"runs": []}}}, "status": "ok", "score": -1}
{"totalTime": 1.6538236141204834, "genResults": {"instance": "gen-inst-21.param", "status": "sat", "seed": 895807196, "SRTime": 0, "solverTime": 0.1103816032409668}, "instanceResults": {"instance": "./detailed-output/inst-21-895807196.dzn", "status": "ok", "score": -1, "results": {"main": {"runs": [{"seed": None, "status": "C", "time": 0.3735313415527344, "extra": {"objs": [], "flattenStatus": "ok", "flattenTime": 0.168594, "instanceType": "unsat", "answerStatus": "unknown"}}]}, "oracle": {"runs": []}}}, "status": "ok", "score": -1}
{"totalTime": 2.785430669784546, "genResults": {"instance": "gen-inst-21.param", "status": "sat", "seed": 930112402, "SRTime": 0.8093891143798828, "solverTime": 0.08354902267456055}, "instanceResults": {"instance": "./detailed-output/inst-21-930112402.dzn", "status": "ok", "score": -1, "results": {"main": {"runs": [{"seed": None, "status": "C", "time": 0.3690760135650635, "extra": {"objs": [], "flattenStatus": "ok", "flattenTime": 0.168251, "instanceType": "unsat", "answerStatus": "unknown"}}]}, "oracle": {"runs": []}}}, "status": "ok", "score": -1}
{"totalTime": 1.6626176834106445, "genResults": {"instance": "gen-inst-22.param", "status": "sat", "seed": 1047895682, "SRTime": 0, "solverTime": 0.11902379989624023}, "instanceResults": {"instance": "./detailed-output/inst-22-1047895682.dzn", "status": "ok", "score": -1, "results": {"main": {"runs": [{"seed": None, "status": "C", "time": 0.3790915012359619, "extra": {"objs": [], "flattenStatus": "ok", "flattenTime": 0.167491, "instanceType": "unsat", "answerStatus": "unknown"}}]}, "oracle": {"runs": []}}}, "status": "ok", "score": -1}
{"totalTime": 1.6514415740966797, "genResults": {"instance": "gen-inst-22.param", "status": "sat", "seed": 1430553564, "SRTime": 0, "solverTime": 0.11997604370117188}, "instanceResults": {"instance": "./detailed-output/inst-22-1430553564.dzn", "status": "ok", "score": -1, "results": {"main": {"runs": [{"seed": None, "status": "C", "time": 0.37328124046325684, "extra": {"objs": [], "flattenStatus": "ok", "flattenTime": 0.169216, "instanceType": "unsat", "answerStatus": "unknown"}}]}, "oracle": {"runs": []}}}, "status": "ok", "score": -1}
{"totalTime": 1.6571629047393799, "genResults": {"instance": "gen-inst-22.param", "status": "sat", "seed": 1828174830, "SRTime": 0, "solverTime": 0.1124715805053711}, "instanceResults": {"instance": "./detailed-output/inst-22-1828174830.dzn", "status": "ok", "score": -1, "results": {"main": {"runs": [{"seed": None, "status": "C", "time": 0.37190866470336914, "extra": {"objs": [], "flattenStatus": "ok", "flattenTime": 0.167472, "instanceType": "unsat", "answerStatus": "unknown"}}]}, "oracle": {"runs": []}}}, "status": "ok", "score": -1}
{"totalTime": 1.6601269245147705, "genResults": {"instance": "gen-inst-22.param", "status": "sat", "seed": 542193560, "SRTime": 0, "solverTime": 0.12063837051391602}, "instanceResults": {"instance": "./detailed-output/inst-22-542193560.dzn", "status": "ok", "score": -1, "results": {"main": {"runs": [{"seed": None, "status": "C", "time": 0.37786316871643066, "extra": {"objs": [], "flattenStatus": "ok", "flattenTime": 0.167557, "instanceType": "unsat", "answerStatus": "unknown"}}]}, "oracle": {"runs": []}}}, "status": "ok", "score": -1}
{"totalTime": 1.6540875434875488, "genResults": {"instance": "gen-inst-22.param", "status": "sat", "seed": 719061008, "SRTime": 0, "solverTime": 0.11310815811157227}, "instanceResults": {"instance": "./detailed-output/inst-22-719061008.dzn", "status": "ok", "score": -1, "results": {"main": {"runs": [{"seed": None, "status": "C", "time": 0.3770115375518799, "extra": {"objs": [], "flattenStatus": "ok", "flattenTime": 0.168493, "instanceType": "unsat", "answerStatus": "unknown"}}]}, "oracle": {"runs": []}}}, "status": "ok", "score": -1}
{"totalTime": 1.643559455871582, "genResults": {"instance": "gen-inst-22.param", "status": "sat", "seed": 895807196, "SRTime": 0, "solverTime": 0.11084914207458496}, "instanceResults": {"instance": "./detailed-output/inst-22-895807196.dzn", "status": "ok", "score": -1, "results": {"main": {"runs": [{"seed": None, "status": "C", "time": 0.3801889419555664, "extra": {"objs": [], "flattenStatus": "ok", "flattenTime": 0.169019, "instanceType": "unsat", "answerStatus": "unknown"}}]}, "oracle": {"runs": []}}}, "status": "ok", "score": -1}
{"totalTime": 2.79500675201416, "genResults": {"instance": "gen-inst-22.param", "status": "sat", "seed": 930112402, "SRTime": 0.8172304630279541, "solverTime": 0.08290457725524902}, "instanceResults": {"instance": "./detailed-output/inst-22-930112402.dzn", "status": "ok", "score": -1, "results": {"main": {"runs": [{"seed": None, "status": "C", "time": 0.37305521965026855, "extra": {"objs": [], "flattenStatus": "ok", "flattenTime": 0.168437, "instanceType": "unsat", "answerStatus": "unknown"}}]}, "oracle": {"runs": []}}}, "status": "ok", "score": -1}
{"totalTime": 1.6489262580871582, "genResults": {"instance": "gen-inst-23.param", "status": "sat", "seed": 1047895682, "SRTime": 0, "solverTime": 0.11467289924621582}, "instanceResults": {"instance": "./detailed-output/inst-23-1047895682.dzn", "status": "ok", "score": -1, "results": {"main": {"runs": [{"seed": None, "status": "C", "time": 0.37868380546569824, "extra": {"objs": [], "flattenStatus": "ok", "flattenTime": 0.168258, "instanceType": "unsat", "answerStatus": "unknown"}}]}, "oracle": {"runs": []}}}, "status": "ok", "score": -1}
{"totalTime": 1.6418893337249756, "genResults": {"instance": "gen-inst-23.param", "status": "sat", "seed": 1430553564, "SRTime": 0, "solverTime": 0.10940432548522949}, "instanceResults": {"instance": "./detailed-output/inst-23-1430553564.dzn", "status": "ok", "score": -1, "results": {"main": {"runs": [{"seed": None, "status": "C", "time": 0.3747091293334961, "extra": {"objs": [], "flattenStatus": "ok", "flattenTime": 0.169946, "instanceType": "unsat", "answerStatus": "unknown"}}]}, "oracle": {"runs": []}}}, "status": "ok", "score": -1}
{"totalTime": 1.6558239459991455, "genResults": {"instance": "gen-inst-23.param", "status": "sat", "seed": 1828174830, "SRTime": 0, "solverTime": 0.11572742462158203}, "instanceResults": {"instance": "./detailed-output/inst-23-1828174830.dzn", "status": "ok", "score": -1, "results": {"main": {"runs": [{"seed": None, "status": "C", "time": 0.37810611724853516, "extra": {"objs": [], "flattenStatus": "ok", "flattenTime": 0.168068, "instanceType": "unsat", "answerStatus": "unknown"}}]}, "oracle": {"runs": []}}}, "status": "ok", "score": -1}
{"totalTime": 1.671344518661499, "genResults": {"instance": "gen-inst-23.param", "status": "sat", "seed": 542193560, "SRTime": 0, "solverTime": 0.11829209327697754}, "instanceResults": {"instance": "./detailed-output/inst-23-542193560.dzn", "status": "ok", "score": -1, "results": {"main": {"runs": [{"seed": None, "status": "C", "time": 0.37976956367492676, "extra": {"objs": [], "flattenStatus": "ok", "flattenTime": 0.176223, "instanceType": "unsat", "answerStatus": "unknown"}}]}, "oracle": {"runs": []}}}, "status": "ok", "score": -1}
{"totalTime": 1.6549792289733887, "genResults": {"instance": "gen-inst-23.param", "status": "sat", "seed": 719061008, "SRTime": 0, "solverTime": 0.10914087295532227}, "instanceResults": {"instance": "./detailed-output/inst-23-719061008.dzn", "status": "ok", "score": -1, "results": {"main": {"runs": [{"seed": None, "status": "C", "time": 0.3787119388580322, "extra": {"objs": [], "flattenStatus": "ok", "flattenTime": 0.168488, "instanceType": "unsat", "answerStatus": "unknown"}}]}, "oracle": {"runs": []}}}, "status": "ok", "score": -1}
{"totalTime": 1.639340877532959, "genResults": {"instance": "gen-inst-23.param", "status": "sat", "seed": 895807196, "SRTime": 0, "solverTime": 0.1144416332244873}, "instanceResults": {"instance": "./detailed-output/inst-23-895807196.dzn", "status": "ok", "score": -1, "results": {"main": {"runs": [{"seed": None, "status": "C", "time": 0.3736433982849121, "extra": {"objs": [], "flattenStatus": "ok", "flattenTime": 0.168029, "instanceType": "unsat", "answerStatus": "unknown"}}]}, "oracle": {"runs": []}}}, "status": "ok", "score": -1}
{"totalTime": 2.8286404609680176, "genResults": {"instance": "gen-inst-23.param", "status": "sat", "seed": 930112402, "SRTime": 0.8287594318389893, "solverTime": 0.08369112014770508}, "instanceResults": {"instance": "./detailed-output/inst-23-930112402.dzn", "status": "ok", "score": -1, "results": {"main": {"runs": [{"seed": None, "status": "C", "time": 0.37400007247924805, "extra": {"objs": [], "flattenStatus": "ok", "flattenTime": 0.169744, "instanceType": "unsat", "answerStatus": "unknown"}}]}, "oracle": {"runs": []}}}, "status": "ok", "score": -1}
{"totalTime": 1.6541845798492432, "genResults": {"instance": "gen-inst-24.param", "status": "sat", "seed": 1047895682, "SRTime": 0, "solverTime": 0.11279749870300293}, "instanceResults": {"instance": "./detailed-output/inst-24-1047895682.dzn", "status": "ok", "score": -1, "results": {"main": {"runs": [{"seed": None, "status": "C", "time": 0.37864232063293457, "extra": {"objs": [], "flattenStatus": "ok", "flattenTime": 0.171526, "instanceType": "unsat", "answerStatus": "unknown"}}]}, "oracle": {"runs": []}}}, "status": "ok", "score": -1}
{"totalTime": 1.6581454277038574, "genResults": {"instance": "gen-inst-24.param", "status": "sat", "seed": 1430553564, "SRTime": 0, "solverTime": 0.11933135986328125}, "instanceResults": {"instance": "./detailed-output/inst-24-1430553564.dzn", "status": "ok", "score": -1, "results": {"main": {"runs": [{"seed": None, "status": "C", "time": 0.37087202072143555, "extra": {"objs": [], "flattenStatus": "ok", "flattenTime": 0.168629, "instanceType": "unsat", "answerStatus": "unknown"}}]}, "oracle": {"runs": []}}}, "status": "ok", "score": -1}
{"totalTime": 1.6347026824951172, "genResults": {"instance": "gen-inst-24.param", "status": "sat", "seed": 1828174830, "SRTime": 0, "solverTime": 0.10921049118041992}, "instanceResults": {"instance": "./detailed-output/inst-24-1828174830.dzn", "status": "ok", "score": -1, "results": {"main": {"runs": [{"seed": None, "status": "C", "time": 0.3783891201019287, "extra": {"objs": [], "flattenStatus": "ok", "flattenTime": 0.167154, "instanceType": "unsat", "answerStatus": "unknown"}}]}, "oracle": {"runs": []}}}, "status": "ok", "score": -1}
{"totalTime": 1.6697123050689697, "genResults": {"instance": "gen-inst-24.param", "status": "sat", "seed": 542193560, "SRTime": 0, "solverTime": 0.1157677173614502}, "instanceResults": {"instance": "./detailed-output/inst-24-542193560.dzn", "status": "ok", "score": -1, "results": {"main": {"runs": [{"seed": None, "status": "C", "time": 0.3775441646575928, "extra": {"objs": [], "flattenStatus": "ok", "flattenTime": 0.169693, "instanceType": "unsat", "answerStatus": "unknown"}}]}, "oracle": {"runs": []}}}, "status": "ok", "score": -1}
{"totalTime": 1.653928518295288, "genResults": {"instance": "gen-inst-24.param", "status": "sat", "seed": 719061008, "SRTime": 0, "solverTime": 0.11574244499206543}, "instanceResults": {"instance": "./detailed-output/inst-24-719061008.dzn", "status": "ok", "score": -1, "results": {"main": {"runs": [{"seed": None, "status": "C", "time": 0.3794069290161133, "extra": {"objs": [], "flattenStatus": "ok", "flattenTime": 0.170432, "instanceType": "unsat", "answerStatus": "unknown"}}]}, "oracle": {"runs": []}}}, "status": "ok", "score": -1}
{"totalTime": 1.6626925468444824, "genResults": {"instance": "gen-inst-24.param", "status": "sat", "seed": 895807196, "SRTime": 0, "solverTime": 0.11868667602539062}, "instanceResults": {"instance": "./detailed-output/inst-24-895807196.dzn", "status": "ok", "score": -1, "results": {"main": {"runs": [{"seed": None, "status": "C", "time": 0.37515878677368164, "extra": {"objs": [], "flattenStatus": "ok", "flattenTime": 0.169059, "instanceType": "unsat", "answerStatus": "unknown"}}]}, "oracle": {"runs": []}}}, "status": "ok", "score": -1}
{"totalTime": 2.778120279312134, "genResults": {"instance": "gen-inst-24.param", "status": "sat", "seed": 930112402, "SRTime": 0.8150732517242432, "solverTime": 0.08387255668640137}, "instanceResults": {"instance": "./detailed-output/inst-24-930112402.dzn", "status": "ok", "score": -1, "results": {"main": {"runs": [{"seed": None, "status": "C", "time": 0.3731083869934082, "extra": {"objs": [], "flattenStatus": "ok", "flattenTime": 0.170143, "instanceType": "unsat", "answerStatus": "unknown"}}]}, "oracle": {"runs": []}}}, "status": "ok", "score": -1}
{"totalTime": 1.665492057800293, "genResults": {"instance": "gen-inst-25.param", "status": "sat", "seed": 1047895682, "SRTime": 0, "solverTime": 0.11281514167785645}, "instanceResults": {"instance": "./detailed-output/inst-25-1047895682.dzn", "status": "ok", "score": -1, "results": {"main": {"runs": [{"seed": None, "status": "C", "time": 0.37998533248901367, "extra": {"objs": [], "flattenStatus": "ok", "flattenTime": 0.168097, "instanceType": "unsat", "answerStatus": "unknown"}}]}, "oracle": {"runs": []}}}, "status": "ok", "score": -1}
{"totalTime": 1.6321430206298828, "genResults": {"instance": "gen-inst-25.param", "status": "sat", "seed": 1430553564, "SRTime": 0, "solverTime": 0.11374878883361816}, "instanceResults": {"instance": "./detailed-output/inst-25-1430553564.dzn", "status": "ok", "score": -1, "results": {"main": {"runs": [{"seed": None, "status": "C", "time": 0.3724517822265625, "extra": {"objs": [], "flattenStatus": "ok", "flattenTime": 0.168028, "instanceType": "unsat", "answerStatus": "unknown"}}]}, "oracle": {"runs": []}}}, "status": "ok", "score": -1}
{"totalTime": 1.6421465873718262, "genResults": {"instance": "gen-inst-25.param", "status": "sat", "seed": 1828174830, "SRTime": 0, "solverTime": 0.11064982414245605}, "instanceResults": {"instance": "./detailed-output/inst-25-1828174830.dzn", "status": "ok", "score": -1, "results": {"main": {"runs": [{"seed": None, "status": "C", "time": 0.3756217956542969, "extra": {"objs": [], "flattenStatus": "ok", "flattenTime": 0.168307, "instanceType": "unsat", "answerStatus": "unknown"}}]}, "oracle": {"runs": []}}}, "status": "ok", "score": -1}
{"totalTime": 1.6476027965545654, "genResults": {"instance": "gen-inst-25.param", "status": "sat", "seed": 542193560, "SRTime": 0, "solverTime": 0.11800551414489746}, "instanceResults": {"instance": "./detailed-output/inst-25-542193560.dzn", "status": "ok", "score": -1, "results": {"main": {"runs": [{"seed": None, "status": "C", "time": 0.3726508617401123, "extra": {"objs": [], "flattenStatus": "ok", "flattenTime": 0.170682, "instanceType": "unsat", "answerStatus": "unknown"}}]}, "oracle": {"runs": []}}}, "status": "ok", "score": -1}
{"totalTime": 1.6405763626098633, "genResults": {"instance": "gen-inst-25.param", "status": "sat", "seed": 719061008, "SRTime": 0, "solverTime": 0.10883355140686035}, "instanceResults": {"instance": "./detailed-output/inst-25-719061008.dzn", "status": "ok", "score": -1, "results": {"main": {"runs": [{"seed": None, "status": "C", "time": 0.3728299140930176, "extra": {"objs": [], "flattenStatus": "ok", "flattenTime": 0.168396, "instanceType": "unsat", "answerStatus": "unknown"}}]}, "oracle": {"runs": []}}}, "status": "ok", "score": -1}
{"totalTime": 1.6511459350585938, "genResults": {"instance": "gen-inst-25.param", "status": "sat", "seed": 895807196, "SRTime": 0, "solverTime": 0.11486673355102539}, "instanceResults": {"instance": "./detailed-output/inst-25-895807196.dzn", "status": "ok", "score": -1, "results": {"main": {"runs": [{"seed": None, "status": "C", "time": 0.37945079803466797, "extra": {"objs": [], "flattenStatus": "ok", "flattenTime": 0.168457, "instanceType": "unsat", "answerStatus": "unknown"}}]}, "oracle": {"runs": []}}}, "status": "ok", "score": -1}
{"totalTime": 2.780971050262451, "genResults": {"instance": "gen-inst-25.param", "status": "sat", "seed": 930112402, "SRTime": 0.8004922866821289, "solverTime": 0.0849611759185791}, "instanceResults": {"instance": "./detailed-output/inst-25-930112402.dzn", "status": "ok", "score": -1, "results": {"main": {"runs": [{"seed": None, "status": "C", "time": 0.37821245193481445, "extra": {"objs": [], "flattenStatus": "ok", "flattenTime": 0.167304, "instanceType": "unsat", "answerStatus": "unknown"}}]}, "oracle": {"runs": []}}}, "status": "ok", "score": -1}
{"totalTime": 1.6607072353363037, "genResults": {"instance": "gen-inst-26.param", "status": "sat", "seed": 1047895682, "SRTime": 0, "solverTime": 0.10932540893554688}, "instanceResults": {"instance": "./detailed-output/inst-26-1047895682.dzn", "status": "ok", "score": -1, "results": {"main": {"runs": [{"seed": None, "status": "C", "time": 0.3787510395050049, "extra": {"objs": [], "flattenStatus": "ok", "flattenTime": 0.169795, "instanceType": "unsat", "answerStatus": "unknown"}}]}, "oracle": {"runs": []}}}, "status": "ok", "score": -1}
{"totalTime": 1.6567156314849854, "genResults": {"instance": "gen-inst-26.param", "status": "sat", "seed": 1430553564, "SRTime": 0, "solverTime": 0.11452150344848633}, "instanceResults": {"instance": "./detailed-output/inst-26-1430553564.dzn", "status": "ok", "score": -1, "results": {"main": {"runs": [{"seed": None, "status": "C", "time": 0.3788762092590332, "extra": {"objs": [], "flattenStatus": "ok", "flattenTime": 0.170843, "instanceType": "unsat", "answerStatus": "unknown"}}]}, "oracle": {"runs": []}}}, "status": "ok", "score": -1}
{"totalTime": 1.6754662990570068, "genResults": {"instance": "gen-inst-26.param", "status": "sat", "seed": 1828174830, "SRTime": 0, "solverTime": 0.12242937088012695}, "instanceResults": {"instance": "./detailed-output/inst-26-1828174830.dzn", "status": "ok", "score": -1, "results": {"main": {"runs": [{"seed": None, "status": "C", "time": 0.37319445610046387, "extra": {"objs": [], "flattenStatus": "ok", "flattenTime": 0.169081, "instanceType": "unsat", "answerStatus": "unknown"}}]}, "oracle": {"runs": []}}}, "status": "ok", "score": -1}
{"totalTime": 1.641237735748291, "genResults": {"instance": "gen-inst-26.param", "status": "sat", "seed": 542193560, "SRTime": 0, "solverTime": 0.1170339584350586}, "instanceResults": {"instance": "./detailed-output/inst-26-542193560.dzn", "status": "ok", "score": -1, "results": {"main": {"runs": [{"seed": None, "status": "C", "time": 0.37801122665405273, "extra": {"objs": [], "flattenStatus": "ok", "flattenTime": 0.168125, "instanceType": "unsat", "answerStatus": "unknown"}}]}, "oracle": {"runs": []}}}, "status": "ok", "score": -1}
{"totalTime": 1.6397790908813477, "genResults": {"instance": "gen-inst-26.param", "status": "sat", "seed": 719061008, "SRTime": 0, "solverTime": 0.11282229423522949}, "instanceResults": {"instance": "./detailed-output/inst-26-719061008.dzn", "status": "ok", "score": -1, "results": {"main": {"runs": [{"seed": None, "status": "C", "time": 0.3758983612060547, "extra": {"objs": [], "flattenStatus": "ok", "flattenTime": 0.171028, "instanceType": "unsat", "answerStatus": "unknown"}}]}, "oracle": {"runs": []}}}, "status": "ok", "score": -1}
{"totalTime": 1.635854959487915, "genResults": {"instance": "gen-inst-26.param", "status": "sat", "seed": 895807196, "SRTime": 0, "solverTime": 0.11055278778076172}, "instanceResults": {"instance": "./detailed-output/inst-26-895807196.dzn", "status": "ok", "score": -1, "results": {"main": {"runs": [{"seed": None, "status": "C", "time": 0.37843918800354004, "extra": {"objs": [], "flattenStatus": "ok", "flattenTime": 0.167759, "instanceType": "unsat", "answerStatus": "unknown"}}]}, "oracle": {"runs": []}}}, "status": "ok", "score": -1}
{"totalTime": 2.7855610847473145, "genResults": {"instance": "gen-inst-26.param", "status": "sat", "seed": 930112402, "SRTime": 0.8134505748748779, "solverTime": 0.08403468132019043}, "instanceResults": {"instance": "./detailed-output/inst-26-930112402.dzn", "status": "ok", "score": -1, "results": {"main": {"runs": [{"seed": None, "status": "C", "time": 0.36971378326416016, "extra": {"objs": [], "flattenStatus": "ok", "flattenTime": 0.17629, "instanceType": "unsat", "answerStatus": "unknown"}}]}, "oracle": {"runs": []}}}, "status": "ok", "score": -1}
{"totalTime": 1.6465129852294922, "genResults": {"instance": "gen-inst-27.param", "status": "sat", "seed": 1047895682, "SRTime": 0, "solverTime": 0.11273980140686035}, "instanceResults": {"instance": "./detailed-output/inst-27-1047895682.dzn", "status": "ok", "score": -1, "results": {"main": {"runs": [{"seed": None, "status": "C", "time": 0.37750744819641113, "extra": {"objs": [], "flattenStatus": "ok", "flattenTime": 0.168023, "instanceType": "unsat", "answerStatus": "unknown"}}]}, "oracle": {"runs": []}}}, "status": "ok", "score": -1}
{"totalTime": 1.6543800830841064, "genResults": {"instance": "gen-inst-27.param", "status": "sat", "seed": 1430553564, "SRTime": 0, "solverTime": 0.11157965660095215}, "instanceResults": {"instance": "./detailed-output/inst-27-1430553564.dzn", "status": "ok", "score": -1, "results": {"main": {"runs": [{"seed": None, "status": "C", "time": 0.37830591201782227, "extra": {"objs": [], "flattenStatus": "ok", "flattenTime": 0.16822, "instanceType": "unsat", "answerStatus": "unknown"}}]}, "oracle": {"runs": []}}}, "status": "ok", "score": -1}
{"totalTime": 1.6663894653320312, "genResults": {"instance": "gen-inst-27.param", "status": "sat", "seed": 1828174830, "SRTime": 0, "solverTime": 0.12694549560546875}, "instanceResults": {"instance": "./detailed-output/inst-27-1828174830.dzn", "status": "ok", "score": -1, "results": {"main": {"runs": [{"seed": None, "status": "C", "time": 0.37831687927246094, "extra": {"objs": [], "flattenStatus": "ok", "flattenTime": 0.172672, "instanceType": "unsat", "answerStatus": "unknown"}}]}, "oracle": {"runs": []}}}, "status": "ok", "score": -1}
{"totalTime": 1.6423397064208984, "genResults": {"instance": "gen-inst-27.param", "status": "sat", "seed": 542193560, "SRTime": 0, "solverTime": 0.11187481880187988}, "instanceResults": {"instance": "./detailed-output/inst-27-542193560.dzn", "status": "ok", "score": -1, "results": {"main": {"runs": [{"seed": None, "status": "C", "time": 0.3741447925567627, "extra": {"objs": [], "flattenStatus": "ok", "flattenTime": 0.171327, "instanceType": "unsat", "answerStatus": "unknown"}}]}, "oracle": {"runs": []}}}, "status": "ok", "score": -1}
{"totalTime": 1.661787509918213, "genResults": {"instance": "gen-inst-27.param", "status": "sat", "seed": 719061008, "SRTime": 0, "solverTime": 0.11742138862609863}, "instanceResults": {"instance": "./detailed-output/inst-27-719061008.dzn", "status": "ok", "score": -1, "results": {"main": {"runs": [{"seed": None, "status": "C", "time": 0.37851810455322266, "extra": {"objs": [], "flattenStatus": "ok", "flattenTime": 0.168418, "instanceType": "unsat", "answerStatus": "unknown"}}]}, "oracle": {"runs": []}}}, "status": "ok", "score": -1}
{"totalTime": 1.6698143482208252, "genResults": {"instance": "gen-inst-27.param", "status": "sat", "seed": 895807196, "SRTime": 0, "solverTime": 0.11717629432678223}, "instanceResults": {"instance": "./detailed-output/inst-27-895807196.dzn", "status": "ok", "score": -1, "results": {"main": {"runs": [{"seed": None, "status": "C", "time": 0.3782353401184082, "extra": {"objs": [], "flattenStatus": "ok", "flattenTime": 0.17458, "instanceType": "unsat", "answerStatus": "unknown"}}]}, "oracle": {"runs": []}}}, "status": "ok", "score": -1}
{"totalTime": 2.7849674224853516, "genResults": {"instance": "gen-inst-27.param", "status": "sat", "seed": 930112402, "SRTime": 0.8142547607421875, "solverTime": 0.08453536033630371}, "instanceResults": {"instance": "./detailed-output/inst-27-930112402.dzn", "status": "ok", "score": -1, "results": {"main": {"runs": [{"seed": None, "status": "C", "time": 0.3744473457336426, "extra": {"objs": [], "flattenStatus": "ok", "flattenTime": 0.169847, "instanceType": "unsat", "answerStatus": "unknown"}}]}, "oracle": {"runs": []}}}, "status": "ok", "score": -1}
{"totalTime": 1.6485717296600342, "genResults": {"instance": "gen-inst-3.param", "status": "sat", "seed": 1047895682, "SRTime": 0, "solverTime": 0.11266255378723145}, "instanceResults": {"instance": "./detailed-output/inst-3-1047895682.dzn", "status": "ok", "score": -1, "results": {"main": {"runs": [{"seed": None, "status": "C", "time": 0.3784470558166504, "extra": {"objs": [], "flattenStatus": "ok", "flattenTime": 0.168739, "instanceType": "unsat", "answerStatus": "unknown"}}]}, "oracle": {"runs": []}}}, "status": "ok", "score": -1}
{"totalTime": 1.6671457290649414, "genResults": {"instance": "gen-inst-3.param", "status": "sat", "seed": 1430553564, "SRTime": 0, "solverTime": 0.11918926239013672}, "instanceResults": {"instance": "./detailed-output/inst-3-1430553564.dzn", "status": "ok", "score": -1, "results": {"main": {"runs": [{"seed": None, "status": "C", "time": 0.37604737281799316, "extra": {"objs": [], "flattenStatus": "ok", "flattenTime": 0.168825, "instanceType": "unsat", "answerStatus": "unknown"}}]}, "oracle": {"runs": []}}}, "status": "ok", "score": -1}
{"totalTime": 1.637441873550415, "genResults": {"instance": "gen-inst-3.param", "status": "sat", "seed": 1828174830, "SRTime": 0, "solverTime": 0.11081743240356445}, "instanceResults": {"instance": "./detailed-output/inst-3-1828174830.dzn", "status": "ok", "score": -1, "results": {"main": {"runs": [{"seed": None, "status": "C", "time": 0.36879849433898926, "extra": {"objs": [], "flattenStatus": "ok", "flattenTime": 0.164363, "instanceType": "unsat", "answerStatus": "unknown"}}]}, "oracle": {"runs": []}}}, "status": "ok", "score": -1}
{"totalTime": 1.643080472946167, "genResults": {"instance": "gen-inst-3.param", "status": "sat", "seed": 542193560, "SRTime": 0, "solverTime": 0.11155891418457031}, "instanceResults": {"instance": "./detailed-output/inst-3-542193560.dzn", "status": "ok", "score": -1, "results": {"main": {"runs": [{"seed": None, "status": "C", "time": 0.37819385528564453, "extra": {"objs": [], "flattenStatus": "ok", "flattenTime": 0.167808, "instanceType": "unsat", "answerStatus": "unknown"}}]}, "oracle": {"runs": []}}}, "status": "ok", "score": -1}
{"totalTime": 2.8606836795806885, "genResults": {"instance": "gen-inst-3.param", "status": "sat", "seed": 719061008, "SRTime": 0.8387024402618408, "solverTime": 0.0855708122253418}, "instanceResults": {"instance": "./detailed-output/inst-3-719061008.dzn", "status": "ok", "score": -1, "results": {"main": {"runs": [{"seed": None, "status": "C", "time": 0.37105751037597656, "extra": {"objs": [], "flattenStatus": "ok", "flattenTime": 0.178471, "instanceType": "unsat", "answerStatus": "unknown"}}]}, "oracle": {"runs": []}}}, "status": "ok", "score": -1}
{"totalTime": 1.679206371307373, "genResults": {"instance": "gen-inst-3.param", "status": "sat", "seed": 895807196, "SRTime": 0, "solverTime": 0.11331605911254883}, "instanceResults": {"instance": "./detailed-output/inst-3-895807196.dzn", "status": "ok", "score": -1, "results": {"main": {"runs": [{"seed": None, "status": "C", "time": 0.37210559844970703, "extra": {"objs": [], "flattenStatus": "ok", "flattenTime": 0.17093, "instanceType": "unsat", "answerStatus": "unknown"}}]}, "oracle": {"runs": []}}}, "status": "ok", "score": -1}
{"totalTime": 1.635382890701294, "genResults": {"instance": "gen-inst-4.param", "status": "sat", "seed": 1047895682, "SRTime": 0, "solverTime": 0.10916399955749512}, "instanceResults": {"instance": "./detailed-output/inst-4-1047895682.dzn", "status": "ok", "score": -1, "results": {"main": {"runs": [{"seed": None, "status": "C", "time": 0.37876129150390625, "extra": {"objs": [], "flattenStatus": "ok", "flattenTime": 0.170041, "instanceType": "unsat", "answerStatus": "unknown"}}]}, "oracle": {"runs": []}}}, "status": "ok", "score": -1}
{"totalTime": 1.6601073741912842, "genResults": {"instance": "gen-inst-4.param", "status": "sat", "seed": 1430553564, "SRTime": 0, "solverTime": 0.11771297454833984}, "instanceResults": {"instance": "./detailed-output/inst-4-1430553564.dzn", "status": "ok", "score": -1, "results": {"main": {"runs": [{"seed": None, "status": "C", "time": 0.3701643943786621, "extra": {"objs": [], "flattenStatus": "ok", "flattenTime": 0.169805, "instanceType": "unsat", "answerStatus": "unknown"}}]}, "oracle": {"runs": []}}}, "status": "ok", "score": -1}
{"totalTime": 1.6665480136871338, "genResults": {"instance": "gen-inst-4.param", "status": "sat", "seed": 1828174830, "SRTime": 0, "solverTime": 0.1091609001159668}, "instanceResults": {"instance": "./detailed-output/inst-4-1828174830.dzn", "status": "ok", "score": -1, "results": {"main": {"runs": [{"seed": None, "status": "C", "time": 0.3789632320404053, "extra": {"objs": [], "flattenStatus": "ok", "flattenTime": 0.168406, "instanceType": "unsat", "answerStatus": "unknown"}}]}, "oracle": {"runs": []}}}, "status": "ok", "score": -1}
{"totalTime": 1.6544904708862305, "genResults": {"instance": "gen-inst-4.param", "status": "sat", "seed": 542193560, "SRTime": 0, "solverTime": 0.1107327938079834}, "instanceResults": {"instance": "./detailed-output/inst-4-542193560.dzn", "status": "ok", "score": -1, "results": {"main": {"runs": [{"seed": None, "status": "C", "time": 0.37859535217285156, "extra": {"objs": [], "flattenStatus": "ok", "flattenTime": 0.168784, "instanceType": "unsat", "answerStatus": "unknown"}}]}, "oracle": {"runs": []}}}, "status": "ok", "score": -1}
{"totalTime": 2.92757511138916, "genResults": {"instance": "gen-inst-4.param", "status": "sat", "seed": 719061008, "SRTime": 0.8794999122619629, "solverTime": 0.08600521087646484}, "instanceResults": {"instance": "./detailed-output/inst-4-719061008.dzn", "status": "ok", "score": -1, "results": {"main": {"runs": [{"seed": None, "status": "C", "time": 0.37395167350769043, "extra": {"objs": [], "flattenStatus": "ok", "flattenTime": 0.177715, "instanceType": "unsat", "answerStatus": "unknown"}}]}, "oracle": {"runs": []}}}, "status": "ok", "score": -1}
{"totalTime": 1.6670513153076172, "genResults": {"instance": "gen-inst-4.param", "status": "sat", "seed": 895807196, "SRTime": 0, "solverTime": 0.11801290512084961}, "instanceResults": {"instance": "./detailed-output/inst-4-895807196.dzn", "status": "ok", "score": -1, "results": {"main": {"runs": [{"seed": None, "status": "C", "time": 0.37125062942504883, "extra": {"objs": [], "flattenStatus": "ok", "flattenTime": 0.170939, "instanceType": "unsat", "answerStatus": "unknown"}}]}, "oracle": {"runs": []}}}, "status": "ok", "score": -1}
{"totalTime": 1.6517105102539062, "genResults": {"instance": "gen-inst-5.param", "status": "sat", "seed": 1047895682, "SRTime": 0, "solverTime": 0.10936880111694336}, "instanceResults": {"instance": "./detailed-output/inst-5-1047895682.dzn", "status": "ok", "score": -1, "results": {"main": {"runs": [{"seed": None, "status": "C", "time": 0.37836503982543945, "extra": {"objs": [], "flattenStatus": "ok", "flattenTime": 0.170484, "instanceType": "unsat", "answerStatus": "unknown"}}]}, "oracle": {"runs": []}}}, "status": "ok", "score": -1}
{"totalTime": 1.659240484237671, "genResults": {"instance": "gen-inst-5.param", "status": "sat", "seed": 1430553564, "SRTime": 0, "solverTime": 0.11664128303527832}, "instanceResults": {"instance": "./detailed-output/inst-5-1430553564.dzn", "status": "ok", "score": -1, "results": {"main": {"runs": [{"seed": None, "status": "C", "time": 0.371762752532959, "extra": {"objs": [], "flattenStatus": "ok", "flattenTime": 0.199308, "instanceType": "unsat", "answerStatus": "unknown"}}]}, "oracle": {"runs": []}}}, "status": "ok", "score": -1}
{"totalTime": 1.6471054553985596, "genResults": {"instance": "gen-inst-5.param", "status": "sat", "seed": 1828174830, "SRTime": 0, "solverTime": 0.1110987663269043}, "instanceResults": {"instance": "./detailed-output/inst-5-1828174830.dzn", "status": "ok", "score": -1, "results": {"main": {"runs": [{"seed": None, "status": "C", "time": 0.3801112174987793, "extra": {"objs": [], "flattenStatus": "ok", "flattenTime": 0.166576, "instanceType": "unsat", "answerStatus": "unknown"}}]}, "oracle": {"runs": []}}}, "status": "ok", "score": -1}
{"totalTime": 1.6338660717010498, "genResults": {"instance": "gen-inst-5.param", "status": "sat", "seed": 542193560, "SRTime": 0, "solverTime": 0.10917091369628906}, "instanceResults": {"instance": "./detailed-output/inst-5-542193560.dzn", "status": "ok", "score": -1, "results": {"main": {"runs": [{"seed": None, "status": "C", "time": 0.3748939037322998, "extra": {"objs": [], "flattenStatus": "ok", "flattenTime": 0.170489, "instanceType": "unsat", "answerStatus": "unknown"}}]}, "oracle": {"runs": []}}}, "status": "ok", "score": -1}
{"totalTime": 2.9216482639312744, "genResults": {"instance": "gen-inst-5.param", "status": "sat", "seed": 719061008, "SRTime": 0.826441764831543, "solverTime": 0.08682513236999512}, "instanceResults": {"instance": "./detailed-output/inst-5-719061008.dzn", "status": "ok", "score": -1, "results": {"main": {"runs": [{"seed": None, "status": "C", "time": 0.39539146423339844, "extra": {"objs": [], "flattenStatus": "ok", "flattenTime": 0.175134, "instanceType": "unsat", "answerStatus": "unknown"}}]}, "oracle": {"runs": []}}}, "status": "ok", "score": -1}
{"totalTime": 1.67622709274292, "genResults": {"instance": "gen-inst-5.param", "status": "sat", "seed": 895807196, "SRTime": 0, "solverTime": 0.11653709411621094}, "instanceResults": {"instance": "./detailed-output/inst-5-895807196.dzn", "status": "ok", "score": -1, "results": {"main": {"runs": [{"seed": None, "status": "C", "time": 0.37268996238708496, "extra": {"objs": [], "flattenStatus": "ok", "flattenTime": 0.173761, "instanceType": "unsat", "answerStatus": "unknown"}}]}, "oracle": {"runs": []}}}, "status": "ok", "score": -1}
{"totalTime": 1.6429693698883057, "genResults": {"instance": "gen-inst-6.param", "status": "sat", "seed": 1047895682, "SRTime": 0, "solverTime": 0.11334013938903809}, "instanceResults": {"instance": "./detailed-output/inst-6-1047895682.dzn", "status": "ok", "score": -1, "results": {"main": {"runs": [{"seed": None, "status": "C", "time": 0.37830615043640137, "extra": {"objs": [], "flattenStatus": "ok", "flattenTime": 0.178404, "instanceType": "unsat", "answerStatus": "unknown"}}]}, "oracle": {"runs": []}}}, "status": "ok", "score": -1}
{"totalTime": 1.68398118019104, "genResults": {"instance": "gen-inst-6.param", "status": "sat", "seed": 1430553564, "SRTime": 0, "solverTime": 0.12292003631591797}, "instanceResults": {"instance": "./detailed-output/inst-6-1430553564.dzn", "status": "ok", "score": -1, "results": {"main": {"runs": [{"seed": None, "status": "C", "time": 0.37163758277893066, "extra": {"objs": [], "flattenStatus": "ok", "flattenTime": 0.173832, "instanceType": "unsat", "answerStatus": "unknown"}}]}, "oracle": {"runs": []}}}, "status": "ok", "score": -1}
{"totalTime": 1.6517810821533203, "genResults": {"instance": "gen-inst-6.param", "status": "sat", "seed": 1828174830, "SRTime": 0, "solverTime": 0.10980772972106934}, "instanceResults": {"instance": "./detailed-output/inst-6-1828174830.dzn", "status": "ok", "score": -1, "results": {"main": {"runs": [{"seed": None, "status": "C", "time": 0.37804722785949707, "extra": {"objs": [], "flattenStatus": "ok", "flattenTime": 0.169414, "instanceType": "unsat", "answerStatus": "unknown"}}]}, "oracle": {"runs": []}}}, "status": "ok", "score": -1}
{"totalTime": 1.662590503692627, "genResults": {"instance": "gen-inst-6.param", "status": "sat", "seed": 542193560, "SRTime": 0, "solverTime": 0.12330174446105957}, "instanceResults": {"instance": "./detailed-output/inst-6-542193560.dzn", "status": "ok", "score": -1, "results": {"main": {"runs": [{"seed": None, "status": "C", "time": 0.3721027374267578, "extra": {"objs": [], "flattenStatus": "ok", "flattenTime": 0.171934, "instanceType": "unsat", "answerStatus": "unknown"}}]}, "oracle": {"runs": []}}}, "status": "ok", "score": -1}
{"totalTime": 2.824739694595337, "genResults": {"instance": "gen-inst-6.param", "status": "sat", "seed": 719061008, "SRTime": 0.8375768661499023, "solverTime": 0.08656620979309082}, "instanceResults": {"instance": "./detailed-output/inst-6-719061008.dzn", "status": "ok", "score": -1, "results": {"main": {"runs": [{"seed": None, "status": "C", "time": 0.37390685081481934, "extra": {"objs": [], "flattenStatus": "ok", "flattenTime": 0.177333, "instanceType": "unsat", "answerStatus": "unknown"}}]}, "oracle": {"runs": []}}}, "status": "ok", "score": -1}
{"totalTime": 1.719799280166626, "genResults": {"instance": "gen-inst-6.param", "status": "sat", "seed": 895807196, "SRTime": 0, "solverTime": 0.12897825241088867}, "instanceResults": {"instance": "./detailed-output/inst-6-895807196.dzn", "status": "ok", "score": -1, "results": {"main": {"runs": [{"seed": None, "status": "C", "time": 0.3716723918914795, "extra": {"objs": [], "flattenStatus": "ok", "flattenTime": 0.175122, "instanceType": "unsat", "answerStatus": "unknown"}}]}, "oracle": {"runs": []}}}, "status": "ok", "score": -1}
{"totalTime": 1.6626613140106201, "genResults": {"instance": "gen-inst-7.param", "status": "sat", "seed": 1047895682, "SRTime": 0, "solverTime": 0.11404871940612793}, "instanceResults": {"instance": "./detailed-output/inst-7-1047895682.dzn", "status": "ok", "score": -1, "results": {"main": {"runs": [{"seed": None, "status": "C", "time": 0.37337779998779297, "extra": {"objs": [], "flattenStatus": "ok", "flattenTime": 0.169729, "instanceType": "unsat", "answerStatus": "unknown"}}]}, "oracle": {"runs": []}}}, "status": "ok", "score": -1}
{"totalTime": 1.9822256565093994, "genResults": {"instance": "gen-inst-7.param", "status": "sat", "seed": 1430553564, "SRTime": 0, "solverTime": 0.41112542152404785}, "instanceResults": {"instance": "./detailed-output/inst-7-1430553564.dzn", "status": "ok", "score": -1, "results": {"main": {"runs": [{"seed": None, "status": "C", "time": 0.3710012435913086, "extra": {"objs": [], "flattenStatus": "ok", "flattenTime": 0.169614, "instanceType": "unsat", "answerStatus": "unknown"}}]}, "oracle": {"runs": []}}}, "status": "ok", "score": -1}
{"totalTime": 1.6823210716247559, "genResults": {"instance": "gen-inst-7.param", "status": "sat", "seed": 1828174830, "SRTime": 0, "solverTime": 0.10903787612915039}, "instanceResults": {"instance": "./detailed-output/inst-7-1828174830.dzn", "status": "ok", "score": -1, "results": {"main": {"runs": [{"seed": None, "status": "C", "time": 0.39547300338745117, "extra": {"objs": [], "flattenStatus": "ok", "flattenTime": 0.172073, "instanceType": "unsat", "answerStatus": "unknown"}}]}, "oracle": {"runs": []}}}, "status": "ok", "score": -1}
{"totalTime": 1.6489038467407227, "genResults": {"instance": "gen-inst-7.param", "status": "sat", "seed": 542193560, "SRTime": 0, "solverTime": 0.11693644523620605}, "instanceResults": {"instance": "./detailed-output/inst-7-542193560.dzn", "status": "ok", "score": -1, "results": {"main": {"runs": [{"seed": None, "status": "C", "time": 0.37470459938049316, "extra": {"objs": [], "flattenStatus": "ok", "flattenTime": 0.168935, "instanceType": "unsat", "answerStatus": "unknown"}}]}, "oracle": {"runs": []}}}, "status": "ok", "score": -1}
{"totalTime": 2.879666805267334, "genResults": {"instance": "gen-inst-7.param", "status": "sat", "seed": 719061008, "SRTime": 0.8370411396026611, "solverTime": 0.08788275718688965}, "instanceResults": {"instance": "./detailed-output/inst-7-719061008.dzn", "status": "ok", "score": -1, "results": {"main": {"runs": [{"seed": None, "status": "C", "time": 0.37133312225341797, "extra": {"objs": [], "flattenStatus": "ok", "flattenTime": 0.177477, "instanceType": "unsat", "answerStatus": "unknown"}}]}, "oracle": {"runs": []}}}, "status": "ok", "score": -1}
{"totalTime": 1.6393101215362549, "genResults": {"instance": "gen-inst-7.param", "status": "sat", "seed": 895807196, "SRTime": 0, "solverTime": 0.09724140167236328}, "instanceResults": {"instance": "./detailed-output/inst-7-895807196.dzn", "status": "ok", "score": -1, "results": {"main": {"runs": [{"seed": None, "status": "C", "time": 0.37117505073547363, "extra": {"objs": [], "flattenStatus": "ok", "flattenTime": 0.171072, "instanceType": "unsat", "answerStatus": "unknown"}}]}, "oracle": {"runs": []}}}, "status": "ok", "score": -1}
{"totalTime": 1.6510958671569824, "genResults": {"instance": "gen-inst-8.param", "status": "sat", "seed": 1047895682, "SRTime": 0, "solverTime": 0.11411261558532715}, "instanceResults": {"instance": "./detailed-output/inst-8-1047895682.dzn", "status": "ok", "score": -1, "results": {"main": {"runs": [{"seed": None, "status": "C", "time": 0.3796052932739258, "extra": {"objs": [], "flattenStatus": "ok", "flattenTime": 0.17042, "instanceType": "unsat", "answerStatus": "unknown"}}]}, "oracle": {"runs": []}}}, "status": "ok", "score": -1}
{"totalTime": 1.6568679809570312, "genResults": {"instance": "gen-inst-8.param", "status": "sat", "seed": 1430553564, "SRTime": 0, "solverTime": 0.10676980018615723}, "instanceResults": {"instance": "./detailed-output/inst-8-1430553564.dzn", "status": "ok", "score": -1, "results": {"main": {"runs": [{"seed": None, "status": "C", "time": 0.3699455261230469, "extra": {"objs": [], "flattenStatus": "ok", "flattenTime": 0.174173, "instanceType": "unsat", "answerStatus": "unknown"}}]}, "oracle": {"runs": []}}}, "status": "ok", "score": -1}
{"totalTime": 1.8486032485961914, "genResults": {"instance": "gen-inst-8.param", "status": "sat", "seed": 1828174830, "SRTime": 0, "solverTime": 0.12050724029541016}, "instanceResults": {"instance": "./detailed-output/inst-8-1828174830.dzn", "status": "ok", "score": -1, "results": {"main": {"runs": [{"seed": None, "status": "C", "time": 0.37212347984313965, "extra": {"objs": [], "flattenStatus": "ok", "flattenTime": 0.170231, "instanceType": "unsat", "answerStatus": "unknown"}}]}, "oracle": {"runs": []}}}, "status": "ok", "score": -1}
{"totalTime": 1.6446342468261719, "genResults": {"instance": "gen-inst-8.param", "status": "sat", "seed": 542193560, "SRTime": 0, "solverTime": 0.11553668975830078}, "instanceResults": {"instance": "./detailed-output/inst-8-542193560.dzn", "status": "ok", "score": -1, "results": {"main": {"runs": [{"seed": None, "status": "C", "time": 0.3780338764190674, "extra": {"objs": [], "flattenStatus": "ok", "flattenTime": 0.16845, "instanceType": "unsat", "answerStatus": "unknown"}}]}, "oracle": {"runs": []}}}, "status": "ok", "score": -1}
{"totalTime": 2.939236879348755, "genResults": {"instance": "gen-inst-8.param", "status": "sat", "seed": 719061008, "SRTime": 0.8590621948242188, "solverTime": 0.08627009391784668}, "instanceResults": {"instance": "./detailed-output/inst-8-719061008.dzn", "status": "ok", "score": -1, "results": {"main": {"runs": [{"seed": None, "status": "C", "time": 0.3771965503692627, "extra": {"objs": [], "flattenStatus": "ok", "flattenTime": 0.177564, "instanceType": "unsat", "answerStatus": "unknown"}}]}, "oracle": {"runs": []}}}, "status": "ok", "score": -1}
{"totalTime": 1.683788537979126, "genResults": {"instance": "gen-inst-8.param", "status": "sat", "seed": 895807196, "SRTime": 0, "solverTime": 0.11789870262145996}, "instanceResults": {"instance": "./detailed-output/inst-8-895807196.dzn", "status": "ok", "score": -1, "results": {"main": {"runs": [{"seed": None, "status": "C", "time": 0.3682241439819336, "extra": {"objs": [], "flattenStatus": "ok", "flattenTime": 0.172775, "instanceType": "unsat", "answerStatus": "unknown"}}]}, "oracle": {"runs": []}}}, "status": "ok", "score": -1}
{"totalTime": 1.6557416915893555, "genResults": {"instance": "gen-inst-9.param", "status": "sat", "seed": 1047895682, "SRTime": 0, "solverTime": 0.11352229118347168}, "instanceResults": {"instance": "./detailed-output/inst-9-1047895682.dzn", "status": "ok", "score": -1, "results": {"main": {"runs": [{"seed": None, "status": "C", "time": 0.37811779975891113, "extra": {"objs": [], "flattenStatus": "ok", "flattenTime": 0.168665, "instanceType": "unsat", "answerStatus": "unknown"}}]}, "oracle": {"runs": []}}}, "status": "ok", "score": -1}
{"totalTime": 1.7011146545410156, "genResults": {"instance": "gen-inst-9.param", "status": "sat", "seed": 1430553564, "SRTime": 0, "solverTime": 0.11043739318847656}, "instanceResults": {"instance": "./detailed-output/inst-9-1430553564.dzn", "status": "ok", "score": -1, "results": {"main": {"runs": [{"seed": None, "status": "C", "time": 0.37987303733825684, "extra": {"objs": [], "flattenStatus": "ok", "flattenTime": 0.175131, "instanceType": "unsat", "answerStatus": "unknown"}}]}, "oracle": {"runs": []}}}, "status": "ok", "score": -1}
{"totalTime": 1.7010164260864258, "genResults": {"instance": "gen-inst-9.param", "status": "sat", "seed": 1828174830, "SRTime": 0, "solverTime": 0.11803388595581055}, "instanceResults": {"instance": "./detailed-output/inst-9-1828174830.dzn", "status": "ok", "score": -1, "results": {"main": {"runs": [{"seed": None, "status": "C", "time": 0.3716464042663574, "extra": {"objs": [], "flattenStatus": "ok", "flattenTime": 0.174743, "instanceType": "unsat", "answerStatus": "unknown"}}]}, "oracle": {"runs": []}}}, "status": "ok", "score": -1}
{"totalTime": 1.6385962963104248, "genResults": {"instance": "gen-inst-9.param", "status": "sat", "seed": 542193560, "SRTime": 0, "solverTime": 0.11085081100463867}, "instanceResults": {"instance": "./detailed-output/inst-9-542193560.dzn", "status": "ok", "score": -1, "results": {"main": {"runs": [{"seed": None, "status": "C", "time": 0.3768775463104248, "extra": {"objs": [], "flattenStatus": "ok", "flattenTime": 0.202737, "instanceType": "unsat", "answerStatus": "unknown"}}]}, "oracle": {"runs": []}}}, "status": "ok", "score": -1}
{"totalTime": 2.9849488735198975, "genResults": {"instance": "gen-inst-9.param", "status": "sat", "seed": 719061008, "SRTime": 0.9310011863708496, "solverTime": 0.08483481407165527}, "instanceResults": {"instance": "./detailed-output/inst-9-719061008.dzn", "status": "ok", "score": -1, "results": {"main": {"runs": [{"seed": None, "status": "C", "time": 0.3690757751464844, "extra": {"objs": [], "flattenStatus": "ok", "flattenTime": 0.171426, "instanceType": "unsat", "answerStatus": "unknown"}}]}, "oracle": {"runs": []}}}, "status": "ok", "score": -1}
{"totalTime": 1.6861557960510254, "genResults": {"instance": "gen-inst-9.param", "status": "sat", "seed": 895807196, "SRTime": 0, "solverTime": 0.11844062805175781}, "instanceResults": {"instance": "./detailed-output/inst-9-895807196.dzn", "status": "ok", "score": -1, "results": {"main": {"runs": [{"seed": None, "status": "C", "time": 0.37054991722106934, "extra": {"objs": [], "flattenStatus": "ok", "flattenTime": 0.172, "instanceType": "unsat", "answerStatus": "unknown"}}]}, "oracle": {"runs": []}}}, "status": "ok", "score": -1}
